Workbook

Sheet Portafolio P&D
A2: N° | B2: Código de Planeamiento | C2: Nombre del Proyecto | D2: Alcance del Proyecto | E2: Gerencia Líder | F2: Líder del Proyecto | G2: Usuario Funcional | H2: Gestor de Planeamiento | I2: Presupuesto asignado | J2: Valor Ganado (EV) | K2: Costo Actual (AC) | L2: CPI | M2: Fecha Comité Ejec. Proy. | N2: N° Acta Comité (aprobación) | O2: Dimensión | P2: Objetivo | Q2: Año Inicio Planificado | R2: Año Fin Planificado | S2: N° Solicitudes de cambio | T2: Componente Tecnológico | U2: Transformación Digital | V2: Cartera | W2: Anexo 1 (Modelo de Negocio) | X2: Líder Técnico | Y2: Fecha Inicio | Z2: Fecha Fin | AA2: % Avance Planificado | AB2: % Avance ejecutado | AC2: Desv. % | AD2: Estado | AE2: SEGUIMIENTO (Planeamiento y Control de Gestión)
A3: 1 | B3: Iniciativa | C3: Nuevo Pagalo.pe | D3: Implementar una nueva web que cumpla con características clave, como la simplicidad, la intuitividad y la modernidad. Permitirá a los clientes y ciudadanos realizar de forma rápida y eficiente sus Operaciones de pago de tasas de manera virtual. | E3: Banca Digital | F3: Lenin Valencia | G3: - | H3: No definido | I3: 1500000 | J3: =Tabla3[[#This Row],[Presupuesto asignado]]/2 -> 750000 | K3: =Tabla3[[#This Row],[Valor Ganado (EV)]] -> 750000 | L3: =Tabla3[[#This Row],[Valor Ganado (EV)]]/Tabla3[[#This Row],[Costo Actual (AC)]] -> 1 | M3: 45121 | N3: No indica | O3: Servicio a los Clientes | P3: De cara al ciudadano | Q3: 2023 | R3: 2025 | S3: 1 | T3: Si | U3: No | V3: Nuevo Págalo | W3: No | X3: Lupe Mayo | Y3: 45139 | Z3: 45852 | AA3: 0 | AB3: 0 | AC3: =Tabla3[[#This Row],[% Avance ejecutado]]-Tabla3[[#This Row],[% Avance Planificado]]/Tabla3[[#This Row],[% Avance Planificado]] -> #DIV/0! | AD3: 04. Cerrado | AE3: 23/05/24 Mediante acta de comité estratégico de proyectos de fecha 06.05.24 se informa que se acordo que el proyecto pasa a estado de "Cerrado", por lo cual deben presentar acta de cierre y lecciones aprendidas. 03/05/2024 Proyecto se encuentra a la espera del Anexo 1 08/04/24 Se realizó cambio de fecha de fin de proyecto de 2024 a 2025 22/03/24 Pendiente que el usuario remita modelo de negocio para registrar el Proyecto en la demanda estrategica priorizada. Modelo de Negocio Observado
A4: 2 | B4: Iniciativa | C4: Nuevo Plataforma App Mobile BN | D4: Implementar una nueva plataforma APP Mobile con funcionalidades adicionales (QR, Pagos) e Integrar más servicios varios a pagar, para ampliar el uso del dinero por canales digitales. A fin de brindar a los usuarios una aplicación y plataforma virtual que les permita migrar sus Operaciones presenciales hacia entornos digitales. | E4: Banca Digital | F4: Lenin Valencia | G4: - | H4: No definido | I4: 2500000 | J4: =Tabla3[[#This Row],[Presupuesto asignado]]/2 -> 1250000 | K4: =Tabla3[[#This Row],[Valor Ganado (EV)]] -> 1250000 | L4: =Tabla3[[#This Row],[Valor Ganado (EV)]]/Tabla3[[#This Row],[Costo Actual (AC)]] -> 1 | M4: 45121 | N4: No indica | O4: Servicio a los Clientes | P4: De cara al ciudadano | Q4: 2023 | R4: 2025 | T4: Si | U4: No | V4: Nuevo APP | W4: No | X4: Alex Valencia | Y4: 44972 | Z4: 45691 | AA4: 0 | AB4: 0 | AC4: =Tabla3[[#This Row],[% Avance ejecutado]]-Tabla3[[#This Row],[% Avance Planificado]]/Tabla3[[#This Row],[% Avance Planificado]] -> #DIV/0! | AD4: 04. Cerrado | AE4: 23/05/24 Mediante acta de comité estratégico de proyectos con fecha 06.05.24 se informa que se aprobo el control de cambios del proyecto y se unificara con Hombe Banking "Multired Virtual", se debe presentar nuevo cronograma- Unifcado. 16/05/2024 Mediante correo de Judit Nino se solicita la revisión de TDRs para su posterior recolección de firmas 15/05/2024 Por correo de Roger Guzman se menciona que se ha completado la abosluciòn de consultas de los participantes el proceso de contrataciòn.Entrega TDR y Excel de consultas. 03/05/2024 En absolución de consultas del proceso Logístico 24/04/2024 Mediante correo remitido por Jorge Guzman se indica los resultados de la reunión del día 19.04 puesto que existen consultas técnicas en el proceso de contratación en la fusión del proyecto y estas deben ser centralizadas y distribuidas por la Oficina de Proyectos y Procesos de TIC. 08/04/24 Se cambia las fechas de inicio y Fin por medidas de control de cambios y unificación de proyecto con "Nueva Homebanking Multired Virtual" 22/03/24 Isabel informa que los Proyectos del Nuevo APP y MV se van a fusionar como un solo proyecto, no será atendido por Fábrica sino se contratará un proveedor. Se observa los entregables asociados a API que se encuentran al 100%, se debe validar si son solo definiciones o implementaciones para sincerar el 41% de avance. Isabel coordinará con Bca DIgital la gestión de cambio de ser necesario. Se debe actualizar además la fecha de inicio y fin en caso corresponda. Isabel agendará una reunión previa con usuario, planemiento y TI. Pendiente que el usuario remita modelo de negocio para registrar el Proyecto en la demanda estrategica priorizada.
A5: 3 | B5: Iniciativa | C5: Nuevo Home Banking "Multired Virtual" | D5: Rediseño e implementación de una Nueva Plataforma con funcionalidades adicionales (Pagos e integrar más servicios varios a pagar), ampliar el uso del dinero por canales digitales. A fin de brindar a los usuarios peruanos una aplicación y plataforma virtual que les permita migrar sus Operaciones presenciales hacia entornos digitales. | E5: Banca Digital | F5: Lenin Valencia | G5: - | H5: No definido | I5: 2500000 | J5: =Tabla3[[#This Row],[Presupuesto asignado]]/2 -> 1250000 | K5: =Tabla3[[#This Row],[Valor Ganado (EV)]] -> 1250000 | L5: =Tabla3[[#This Row],[Valor Ganado (EV)]]/Tabla3[[#This Row],[Costo Actual (AC)]] -> 1 | M5: 45121 | N5: No indica | O5: Servicio a los Clientes | P5: De cara al ciudadano | Q5: 2023 | R5: 2025 | T5: Si | U5: No | V5: Nuevo HB | W5: No | X5: Alex Valencia | Y5: 44972 | Z5: 45691 | AA5: 0 | AB5: 0 | AC5: =Tabla3[[#This Row],[% Avance ejecutado]]-Tabla3[[#This Row],[% Avance Planificado]]/Tabla3[[#This Row],[% Avance Planificado]] -> #DIV/0! | AD5: 04. Cerrado | AE5: 23/05/24 Mediante acta de comité estratégico de proyectos con fecha 06.05.24 se informa que se aprobo el control de cambios del proyecto y se unificara con Hombe Banking "Multired Virtual", se debe presentar nuevo cronograma- Unifcado. 16/05/2024 Mediante correo de Judit Nino se solicita la revisión de TDRs para su posterior recolección de firmas 15/05/2024 Por correo de Roger Guzman se menciona que se ha completado la abosluciòn de consultas de los participantes el proceso de contrataciòn.Entrega TDR y Excel de consultas. 03/05/2024 En absolución de consultas del proceso Logístico 24/04/2024 Mediante correo remitido por Jorge Guzman se indica los resultados de la reunión del día 19.04 puesto que existen consultas técnicas en el proceso de contratación en la fusión del proyecto y estas deben ser centralizadas y distribuidas por la Oficina de Proyectos y Procesos de TIC. 08/04/024 Existe un control de cambios y un plan de unificación con el proyecto "Nuevo APP BN" 22/03/24 Idem Nuevo APP BN
A6: 4 | B6: Iniciativa | C6: Nuevo Agente Corresponsal / Pago de Tasas | D6: Implementación de una nueva plataforma móvil para la administración y gestión de la Red de Agentes Corresponsales. Permite realizar Operaciones como depósitos, retiros y pagos de tasas a través de dispositivos móviles, brindando mayor independencia y control al Banco en la atención y configuración de los agentes. Mejora la eficiencia y calidad del servicio, ofreciendo una experiencia más conveniente para los clientes. | E6: Banca Digital | F6: Lenin Valencia | G6: Alexis Junchaya | H6: No definido | I6: 550000 | J6: =Tabla3[[#This Row],[Presupuesto asignado]]/2 -> 275000 | K6: =Tabla3[[#This Row],[Valor Ganado (EV)]] -> 275000 | L6: =Tabla3[[#This Row],[Valor Ganado (EV)]]/Tabla3[[#This Row],[Costo Actual (AC)]] -> 1 | M6: 45121 | N6: No indica | O6: Servicio a los Clientes | P6: De cara al ciudadano | Q6: 2023 | R6: 2025 | T6: Si | U6: No | V6: Nuevo Agente | W6: No | X6: Juan Ortega | Y6: 45127 | Z6: 45821 | AA6: 0 | AB6: 0 | AC6: =Tabla3[[#This Row],[% Avance ejecutado]]-Tabla3[[#This Row],[% Avance Planificado]]/Tabla3[[#This Row],[% Avance Planificado]] -> #DIV/0! | AD6: 04. Cerrado | AE6: 23/05/24 Mediante acta de comité estratégico de proyectos con fecha 06.05.24 se informa que se acordo que el proyecto pasa a estado de "Cerrado" , por lo cual deben presentar acta de cierre y lecciones aprendidas. 03/05/2024 A la espera de del Anexo 1 Modelo de Negocio 08/04/24 Se cambia la fecha de Fin de proyecto de 2024 a 2025 20/3/2024 Usuario se encuentran avanzando con su primer entregable que son las TDRs. Pendiente que el usuario remita modelo de negocio para registrar el Proyecto en la demanda estrategica priorizada. Modelo de Negocio Observado
A7: 5 | B7: PROKDD-EO05-23-4 | C7: Pruebas de Concepto - Quiosko digital dispensador de tarjetas | D7: La implementacion de los quioscos digitales brindará terminales de autoservicio para que los clientes puedan interactuar con informacion y contenido digital con el fin de facilitar y acelerar sus solicitudes y requerimientos, los cuales actualmente se hacen de forma presencial. | E7: Banca Digital | F7: Marita Carbajo | G7: Por definir | H7: Noe Figueroa | I7: S/ 1.659,450 | J7: =Tabla3[[#This Row],[Presupuesto asignado]]/2 -> #VALUE! | K7: =Tabla3[[#This Row],[Valor Ganado (EV)]] -> #VALUE! | L7: =Tabla3[[#This Row],[Valor Ganado (EV)]]/Tabla3[[#This Row],[Costo Actual (AC)]] -> #VALUE! | M7: 45121 | N7: Acta Nº8-2023 | O7: Servicio a los Clientes | P7: De cara al ciudadano | Q7: 2023 | R7: 2026 | S7: 5 | T7: Si | U7: Sí | V7: Quiosco Multimedia | W7: Si | X7: Jorge Campos | Y7: 45110 | Z7: 46081 | AA7: 0.88 | AB7: 0.85 | AC7: =Tabla3[[#This Row],[% Avance ejecutado]]-Tabla3[[#This Row],[% Avance Planificado]]/Tabla3[[#This Row],[% Avance Planificado]] -> -0.15 | AD7: 02. En Curso | AE7: 14/04/2026: En el mes de marzo, al cierre se vienen realizando pruebas funcionales y técnicas en ambiente de desarrollo; sin embargo, las pruebas funcionales presentaron retrasos por inestabilidad del ambiente y demoras en levantar observaciones por parte de TI. 23/03/2026: Al cierre del mes de febrero de 2026 se vienen realizando pruebas funcionales y técnicas en ambiente de desarrollo. 20/03/2026: Según el acta de reunión del comité de proyectos del mes de enero, el proyecto presentó un ligero retraso al cierre de diciembre 2025, no completándose las pruebas en ambiente de BN Banco. El proveedor ha solicitado 3 ampliaciones a la fecha y mantiene un atraso de un mes en las pruebas de desarrollo, lo cual impactará en el cronograma planificado actual. 25/02/2026: Al cierre de enero de 2026 se registró un retraso atribuible al proveedor que impidió completar la implementación del ambiente de desarrollo para las pruebas de BN Banco. El proveedor solicitó tres ampliaciones de plazo (12, 28 y 13 días), aprobándose 12, 18 y 8 días, respectivamente; sin embargo, mantiene un retraso aproximado de un mes, lo que afecta el cronograma del proyecto, por lo que se viene preparando un control de cambios para sincerar los plazos. 21/01/2026: Se han concluido la configuración y desarrollo de la aplicación en el equipo, dando lugar a las coordinaciones e inicio de las pruebas en ambiente de desarrollo. 30/11/2025: Se han concluido la revisión de las APIS desarrolladas para la integración del quiosco con el CORE Banco; se están haciendo las coordinaciones para el inicio de las pruebas en ambiente de desarrollo (preparación ambiente). 31/10/2025: Según la información enviada de Planeamiento en el mes de Octubre se precisa lo siguiente: "Al cierre de octubre, el Quiosco Multimedia trasladado al laboratorio del Banco se encuentra en proceso de instalación, configuración y desarrollo de la aplicación, en coordinación con las áreas técnicas y funcionales. Se registraron retrasos en actividades del Hito 3 relacionadas con la integración y pruebas del sistema; sin embargo, se prevé su recuperación mediante la ejecución en paralelo de los entregables “Configuración de Bienes y Pase a Producción” y “Desarrollo y Puesta en Producción de Transacciones”. Se envió 01 quioscos adicional en el laboratorio. En ese contexto, se viene solicitando un control de cambio para sincerar los plazos y optimizar la gestión del cronograma, asegurando la continuidad y calidad del proyecto." 30/09/2025: Según la información enviada de Planeamiento en el mes de Septiembre se precisa lo siguiente: Al cierre de Septiembre, el Quiosco Multimedia trasladado al laboratorio del Banco se encuentra en proceso de instalación, configuración y desarrollo de la aplicación, en coordinación con las áreas técnicas y funcionales. Se registraron retrasos en actividades del Hito 3 relacionadas con la integración y pruebas del sistema. Sin embargo, se prevé su recuperación mediante la ejecución en paralelo de los entregables “Configuración de Bienes y Pase a Producción” y “Desarrollo y Puesta en Producción de Transacciones”. En ese contexto, se viene solicitando un control de cambio para sincerar los plazos y optimizar la gestión del cronograma, asegurando la continuidad y calidad del proyecto. 16/09/2025: Según la información enviada de Planeamiento en el mes de Agosto se precisa lo siguiente: Al cierre de agosto, el Quiosco multimedia trasladado al laboratorio del Banco (Sede principal), se encuentra en proceso de instalación, configuración y desarrollo de la aplicación por parte del contratista (hardware y software), en coordinación con las áreas técnica y funcional. Si bien se han registrado retrasos en las actividades: Instalación de Quioscos en laboratorio, Construcción Transacción Reposición y actualización de datos, Pruebas en ambiente de desarrollo, Acta de Conformidad en Desarrollo y Pruebas en ambiente de certificación del proyecto, se prevé su recuperación mediante la ejecución en paralelo de las primeras dos actividades de los siguientes entregables planificados. · Entregable: Configuración de Bienes y Pase a Producción · Entregable: Desarrollo y puesta en producción de transacciones La ejecución simultánea de estas actividades permitirá optimizar los tiempos, reducir el impacto de los retrasos registrados y asegurar la continuidad del cronograma. 18/08/25: Según la información enviada de Planeamiento en el mes de Julio se precisa lo siguiente: Al cierre del mes de julio, se culminó la verificación de los bienes.(03 quioscos multimedia) que se encuentran internados en el almacén del Banco. 18/07/25: Al 30.06.25, se vienen realizando actividades relacionadas a la verificación de los bienes que se encuentran internados en el almacén del Banco. Se estima concluir con la verificación en el mes de agosto de acuerdo a lo planificado. Asimismo, se concluyó el modelo funcional, lo que corresponde a la actividad interna paralela que se efectúa en coordinación con el proveedor fabricante de los Quioscos. 07/07/2025: Los Informes de Conformidad de equipos se encuentran en proceso de emision para ser reportados a Banca Digital. 11/06/2025:Según la información enviada de Planeamiento en el mes de Mayo se precisa lo siguiente: Las áreas de Sección Soporte de la Infraestructura Tecnológica y Atención a Usuario, Sección Sistemas Bancarios, Sección Canales Presenciales y Subgerencia de Innovación digital ya verificaron los equipos de quioscos multimedia ingresados al almacén del Banco y está en proceso la firma de las actas de conformidad respectivas de cada área. Se espera tener el flujo funcional cerrado, para ello se esta realizando las reuniones de entendimiento entre las áreas responsables. 03/06/2025: Según la información enviada de Planeamiento mediante correo respecto al proyecto en el mes de abril se tiene que: Se recepcionó los quioscos multimedia en el almacén del Banco y se inició las coordinaciones para proceder a la verificación de los equipos durante el mes de mayo. Cabe resaltar que el proveedor efectuó la referida entrega con antelación, dado que estuvo planificada para el mes de julio. 07/05/2025: Según la información enviada por Planeamiento mediante correo: Se encuentra en proceso la definición del esquema de integración de los quioscos con el core del Banco para la transacción de reposición de tarjeta, lo que permitirá continuar con las actividades que se tenían planificadas, 31/12/2024: Se completó la firma del contrato con la empresa ganadora y se tiene un cronograma con control de cambios aprobado por el Comité de proyectos 23/05/24 Mediante comité estratégico del proyecto con fecha 06.05.24 se informa que se aprobó el control de cambios, que implica un nuevo cronograma; el alcance se mantiene. 15/05/2024 Mediante correo de Marita Carbajo entrega ETMS actualizados y deja constancia que con memo N°568-2024-BN-2662 hay consultas de Belltech de ser necesarias agregarlas a ETMS. 02/05/2024 Mediante correo de Hector Sevalla se da a conocer los temas e implementaciones que puede tener el proyecto, se deja en conocimiento la inclusión a un sistema ESP/LINK, aumento de funcionalidades de ATM e inclusión de BEVERTEC. A la espera de agendarse reunión para 02.05 y consolidar los temas pendientes. 26/04/2024 Mediante correo se espera la actualización del documento Anexo 1 que debe ser remitido por el área correspondiente por tener observaciones en el nombre del proyecto y falta de fecha del proyecto. Asi mismo, se espera la solicitud de validación del cronograma del proyecto. Mediante correo se pide reagendar reunión y confirmar la asistencia a esta del Subgerente de Construcción de aplicaciones. 25/04/2024 Mediante correo de Marita Carbajo se da conocimiento de la consulta en coordinacion de Construcción de aplicaciones y el proveedor sobre el intercambio de llaves para que el Kiosko se comporte como un ATM. Se pide agendar reunión para el 26.04 con miembros de TI 24/04/2024 Se entrega vía correo por parte de Marita Carbajo el Anexo 1"Modelo de Negocio". 24/04/2024 Se recibe el correo envíado por Marita Carbajo en el que se notifica la entrega de documentación de Viabilidad Técnica, Modelo funcional y Cronograma del proyecto. Se pide enviar el Modelo de Negocio - Anexo 1 08/04/24 Se realizó cambio de fecha de fin de proyecto de 2023 a 2025 20/03/24 Usuario se encuentra resolviendo las observaciones de las ETMs en coordinación con Logística. Habra un control de cambios, en base al cronograma que presentará el usuario. Pendiente que el usuario remita modelo de negocio para registrar el Proyecto en la demanda estrategica priorizada. Modelo de Negocio Observado
A8: 6 | B8: PRONCR-EO05-23-5 | C8: Pruebas de concepto Cajeros Automáticos Depositarios | D8: La implementacion de los cajeros automaticos para deposito y retiro como prueba de concepto, busca brindar a los clientes una alternativa para que puedan realizar retiros y depositos en horarios distintos al de las agencias logrando de esta manera promover una cultura de autoservicio y una gestion eficeinte del canal | E8: Banca Digital | F8: Diego Marcelo | G8: Por definir | H8: Juan Carlos Palomino | I8: 866957 | J8: 500000 | K8: 800000 | L8: =Tabla3[[#This Row],[Valor Ganado (EV)]]/Tabla3[[#This Row],[Costo Actual (AC)]] -> 0.625 | M8: 45121 | N8: Acta Nº8-2023 | O8: Servicio a los Clientes | P8: De cara al ciudadano | Q8: 2023 | R8: 2026 | S8: 4 | T8: Si | U8: Sí | V8: Cajeros Depositarios | W8: Si | X8: Felix Ochoa | Y8: 45071 | Z8: 46295 | AA8: 0.87 | AB8: 0.84 | AC8: =Tabla3[[#This Row],[% Avance ejecutado]]-Tabla3[[#This Row],[% Avance Planificado]]/Tabla3[[#This Row],[% Avance Planificado]] -> -0.16 | AD8: 02. En Curso | AE8: 14/04/2026: En el mes de marzo, actualmente nos encontramos en la fase de desarrollo e integración de las soluciones: Transacción de Depósito en efectivo sin tarjeta, procesos Batch FISA, DAPH y Contabilización de ATM, así como alertas de Card Reader y RMV4 en consola Truesight; no se han evidenciado retrasos en los desarrollos asociados y, en conjunto con el área de Planeamiento, se realizan seguimientos semanales del proyecto. 23/03/2026: Al cierre de febrero, se está avanzando en la implementación de los flujos principales de depósito (sin tarjeta y contactless), validando las pantallas en front-end para asegurar la mensajería y experiencia de usuario, y definiendo los flujos batch en el backend. 20/03/2026: Según el acta de reunión del comité de proyectos del mes de enero, el proyecto marchó de acuerdo a lo planificado al cierre de diciembre 2025. A la fecha, la Gerencia de Banca Digital ya cuenta con un cronograma detallado del entregable "Configuración de bienes", el cual está siendo firmado por todos los participantes. 21/01/2026: Se identificaron componentes compartidos con Esplink que impactan al proyecto Card Dispenser, por lo que se acordó la coexistencia de cambios en el ambiente de desarrollo y la ejecución de validaciones en ventanas programadas. Se confirmó el despliegue de la integración con el Backend del banco para el viernes 02/01/2026 para iniciar las validaciones de la primera transacción de depósito con tarjeta el lunes 05/01/2026. 30/11/2025: "En el marco del Proyecto Cajeros Depositarios, se realizó el sinceramiento de la ponderación de los avances del proyecto por hito, lo cual fue revisado y discutido en la Reunión del 5 de diciembre, y reflejado en la Ficha de Seguimiento Parte A y Parte B (CC). No obstante, dicho ajuste no fue aprobado en el presente periodo, debido a que corresponde ser gestionado a través del proceso formal de Control de Cambios. Durante la revisión, se identificó que la actualización del porcentaje en la sección Configuración de Bienes al 55% generó un ajuste automático del avance planificado a 35%, manteniéndose alineado con el avance ejecutado, considerando que la fase de Implementación concentra mayor esfuerzo y complejidad. Actualmente, las actividades de configuración de los equipos del proyecto se ejecutan conforme al cronograma aprobado, dentro de los plazos establecidos y sin desviaciones relevantes. El Control de Cambios correspondiente será presentado para su evaluación en el mes de enero de 2026, conforme a lo acordado." 31/10/2025: Según la información enviada de Planeamiento en el mes de Octubre se precisa lo siguiente: Actualmente nos encontramos en la fase de implementación de las configuraciones del Software en el Cajero automático depositario, así mismo, venimos gestionando en conjunto con la empresa Bevertec el inicio de la implementación de la solución en la plataforma Esplink la cual se encuentra en la fase de revisión y aprobación del PCR. 30/09/2025: Según la información enviada de Planeamiento en el mes de Septiembre se precisa lo siguiente: Durante este mes se realizó la verificación física de los equipos, de los cuales en la primera revisión se encontraron observaciones las cuales fueron subsanadas por el proveedor Diebold generando una segunda fase de validación la cual fue conforme. 16/09/2025:Según la información enviada de Planeamiento en el mes de Agosto se precisa lo siguiente: Se efectuó la entrega de los cinco (05) cajeros depositarios conforme a lo programado. Actualmente, el proyecto se encuentra en la fase de verificación física de los equipos, previa a su puesta en funcionamiento. 18/08/25: Según la información enviada de Planeamiento en el mes de Julio se precisa lo siguiente: Monitoreo de entrega de equipos: Al terminar julio, siguen vigilando que los equipos (cajeros depositarios) se entreguen en las fechas acordadas Reuniones técnicas: Se sostuvieron reuniones de trabajo con el equipo de TI y el proveedor con el objetivo de revisar aspectos técnicos y funcionales clave para la implementación de los Cajeros Depositarios. Definición del flujo de transacciones: Se viene definiendo el flujo final de la transacción de depósito, incluyendo los escenarios de excepción, tanto para transacciones parciales como fallidos (por ejemplo, si el cliente no termina de ingresar todo el dinero). Transacciones que se habilitarán con Contactless (tarjeta o dispositivo sin contacto físico). Se encuentra en actualización el anexo N° 1 en el cual se incorporarán los requerimientos funcionales adicionales identificados. 13/08/2025: De acuerdo al Acta de Comité de Proyectos del 16/07 N°06-2025 se informa que: Se aprueba la solicitud de cambio con el presupuesto actualizado que asciende a S/866,956.74. 18/07/2025: Al 30.06.25, se viene realizando : -El seguimiento al proveedor para garantizar que la entrega de los equipos se realice oportunamente y con la calidad esperada. -Sesiones técnicas con el proveedor, avanzando las actividades de integración de la solución conjuntamente con TI; y en esos espacios se realiza el seguimiento de las fechas de la entrega de los bienes. Presentó CC por el presupuesto del proyecto. 07/07/2025: Actualmente se vienen desarrollando sesiones de trabajo conjuntas con la Gerencia de Tecnologías de Información y el proveedor Diebold, orientadas al diseño de la arquitectura de la solución y la gestión de los componentes de TI, en paralelo a la espera de la recepción física de los bienes. Asimismo sesiones con area usuario para definir el flujo funcional. 11/06/2025:Según la información enviada de Planeamiento en el mes de Mayo se precisa lo siguiente: Se están realizando sesiones de trabajo para el diseño de la arquitectura de solución y gestión de componente de TI en conjunto con el equipo de la Gerencia de Tecnologías de Información y el proveedor Diebold, mientras se espera la recepción física de los bienes. 03/06/2025: Según la información enviada de Planeamiento mediante correo respecto al proyecto al mes de abril se tiene que: Se realizó la firma correspondiente del contrato con el postor ganador Diebold Nixdorf Perú SRL., asimismo, se llevó a cabo la ceremonia del Kickoff con las áreas correspondientes. 07/05/2025: Según la información remitida por Planeamiento mediante correo: Para lograr el perfeccionamiento del contrato, el postor ganador Diebold logró subsanar las observaciones de la respectiva documentación en coordinación con el área de Logística e Innovación Digital, lo cual permitirá que la firma de contrato se pueda concretar dentro de los plazos previstos. 31/01/25: Para lograr el perfeccionamiento del contrato, el postor ganador Diebold logró subsanar las observaciones de la respectiva documentación en coordinación con el área de Logística e Innovación Digital, lo cual permitirá que la firma de contrato se pueda concretar dentro de los plazos previstos.En absolución de consultas y observaciones hasta este viernes 31ene25. 31/12/2024: Al 13.12.2024 se encuentra en proceso de reformulación de ETMs por resolución del Tribunal OSCE declaró nulo el proceso de selección (05.12.2024). El 27.12.2024 se convocó en el SEACE la LP-SM-4-2024-BN-1 23/05/24 Mediante acta de comité estratégico de proyectos con fecha 06.05.24 se aprobó el control de cambios del alcance del proyecto, los usuarios deben formalizar el nuevo cronograma del proyecto y remitirlo a planeamiento. 03/05/2024 Se ha devuelto Anexo 1 con observaciones 26/04/2024 Mediante correo de Pablo Arias se entrega el Anexo 1 del proyecto, el cuál se devuelve con observaciones notificadas dentro del documeneto al remitente en mención. A la espera de la devolución con observaciones levantadas, firmado y remitido por STD. 26/04/2024 A la espera de remitirse a TI el Anexo 1 y Anexo 2, asi mismo el registro de los requerimientos en OPP para su posterior categorización de cartera. 25/04/2024 Mediante Memo N° 63-2024-BN2810 en que se entrega la nueva lista de proyectos con componente TI se crea el proyecto en base de datos y se asigna el Lider usuario al proyecto, anteriormente no existia.
A9: 7 | B9: PRODNI-EO12-23-8 | C9: Proyecto Cuenta DNI – Nuevas Funcionalidades | D9: La cuenta DNI es una cuenta básica de ahorros de naturaleza digital y en moneda nacional | E9: Banca Digital | F9: Luis Palacios | G9: Por definir | H9: Juan Carlos Palomino | I9: 31894424 | J9: 500000 | K9: 400000 | L9: =Tabla3[[#This Row],[Valor Ganado (EV)]]/Tabla3[[#This Row],[Costo Actual (AC)]] -> 1.25 | M9: 45121 | N9: Acta Nº8-2023 | O9: Servicio a los Clientes | P9: De cara al ciudadano | Q9: 2023 | R9: 2025 | S9: 5 | T9: Si | U9: Sí | V9: Cuenta DNI (Cloud) | W9: Si | X9: Angela Risco | Y9: 45065 | Z9: 46112 | AA9: 0.76 | AB9: 0.71 | AC9: =Tabla3[[#This Row],[% Avance ejecutado]]-Tabla3[[#This Row],[% Avance Planificado]]/Tabla3[[#This Row],[% Avance Planificado]] -> -0.29 | AD9: 02. En Curso | AE9: 14/04/2026: En el mes de marzo, respecto a la ETAPA I: MVP2 (salida), se levantó la observación al Workbook por la CCE, lo que implicó un nuevo desarrollo por parte del proveedor Backbase y pruebas adicionales en ambiente de Calidad para la certificación y pase a producción de las funcionalidades: Transferencias interbancarias inmediatas de salida, Transferencias por contacto de salida y Transferencias mediante código QR de salida (canal móvil). 23/03/2026: En la ETAPA I (MVP2 salida) de Cuenta DNI, una observación de la CCE al Workbook requirió un nuevo desarrollo por Backbase y pruebas adicionales en Calidad, impactando las transferencias de salida (interbancarias inmediatas, por contacto y vía QR). 20/03/2026: Según el acta de reunión del comité de proyectos del mes de enero, el proyecto presentó un ligero retraso al cierre de diciembre 2025. Si bien el MVP2 completó el 100% de las pruebas funcionales en noviembre 2025, la Gerencia de TI solicitó a fines de diciembre realizar pruebas de vulnerabilidad a las APIs de Temenos. Se estima culminar el MPV2 para el mes de enero 2026. Asimismo, el Comité de Cuenta DNI debe evaluar y definir las acciones correspondientes respecto al proyecto. 25/02/2026: En la ETAPA I – MVP2 (salida) del proyecto Cuenta DNI se vienen ejecutando las validaciones de reportes contables para asegurar el correcto registro financiero de las nuevas funcionalidades. El proyecto se encuentra pendiente de aprobación de la Cámara de Compensación para autorizar el pase a producción de las funcionalidades de transferencias de salida, que incluyen transferencias interbancarias inmediatas, por contacto y mediante código QR. 21/01/2026: El MVP2 completó satisfactoriamente el 100 % de las pruebas funcionales en noviembre de 2025. Actualmente, el proyecto se encuentra en la fase de validación de reportes contables, con incidencias siendo analizadas y corregidas. Adicionalmente, la Gerencia de TI solicitó el 24/12/2025 la ejecución de pruebas de vulnerabilidad sobre las APIs de Temenos, las cuales se encuentran en proceso de ejecución. 31/10/2025: Según la información enviada de Planeamiento en el mes de Octubre se precisa lo siguiente: Se ha presentado una solicitud de cambio donde se estará llevando un mejor control del avance del proyecto, hasta el momento se han mantenido las fechas con los avances porcentuales correspondientes. 30/09/2025: Según la información enviada de Planeamiento en el mes de Septiembre se precisa lo siguiente: El proyecto presenta retrasos principalmente por dependencias externas con los proveedores Temenos, Backbase y Novatronic, cuyos servicios aún se encuentran en fase de pruebas en el ambiente de certificación. Se ha presentado una solicitud de cambio con el objetivo de establecer un mejor control del avance del proyecto. Hasta el momento, se vienen manteniendo las fechas establecidas, con los avances porcentuales correspondientes conforme al cronograma vigente. 16/09/2025: Según la información enviada de Planeamiento en el mes de Agosto se precisa lo siguiente: Debido a la suspensión temporal del servicio por parte de los proveedores, el proyecto se vio afectado en su cronograma de pruebas. Sin embargo, tras regularizar los pagos correspondientes, el servicio fue restablecido y se han retomado las pruebas de manera satisfactoria, dando continuidad a la ejecución del proyecto. 21/08/2025: De acuerdo al Acta de Comité de Proyectos del 14/08 N°07-2025 se informa que: Se solicita a la Gerencia de Banca Digital realizar un informe situacional del proyecto y formalizar su solicitud de cambio para el próximo Comité Ejecutivo de Proyectos. Además, se solicita una reunión entre la Gerencia de Banca Digital, Gerencia Legal y la Gerencia de Administración y Logística para revisar el contrato con los proveedores del proyecto. Preliminar a ello, la Gerencia de Banca Digital debe confirmar si tuvo algún tipo de comunicación con los proveedores en relación con el contrato. 18/08/25: Según la información enviada de Planeamiento en el mes de Julio se precisa lo siguiente: El proyecto avanza conforme al road map (Hoja de Ruta) establecido; sin embargo, se registran demoras en las pruebas integrales debido a la alta complejidad de la integración entre BackBase, Temenos, Novatronic y CCE, así como a inconvenientes en los pagos a proveedores, lo que ha afectado la continuidad de las actividades. Se avanza en la configuración del servidor que gestionará las tarifas aplicables a las transferencias inmediatas, elemento clave para garantizar el correcto cálculo y aplicación de comisiones en la operación del servicio. 13/08/2025: De acuerdo al Acta de Comité de Proyectos del 16/07 N°06-2025 se informa que: la Gerencia de Banca Digital indicó que el proyecto terminará a fines de octubre 2025. En virtud de ello, se solicita el apoyo de todos los participantes para culminar en el periodo mencionado. 18/07/2025: Se están realizando pruebas en el ambiente de calidad de las funcionalidades de transferencias interbancarias inmediatas y pagos con QR, con los tres proveedores involucrados: Backbase, Temenos y Novatronic. Durante estas pruebas se han identificado incidencias relacionadas con la conexión a la Cámara de Compensaciones Electrónicas (CCE), debido a que se trata de un servicio compartido entre las áreas de TI. • El pase a producción está programado para agosto del MPV2 y para noviembre del MPV3 . • Actualmente se vienen desarrollando reuniones de seguimiento con el objetivo de supervisar el avance y la resolución de incidencias durante las pruebas. 11/06/2025:Según la información enviada de Planeamiento en el mes de Mayo se precisa lo siguiente: Durante la ejecución de las pruebas integrales en el entorno de desarrollo, en las que participan los tres proveedores (Backbase, Temenos y Novatronic), se han identificado incidencias relacionadas con la conexión a la Cámara de Compensaciones y con los tiempos de respuesta en las operaciones correspondientes al proceso de interoperabilidad (transferencias interbancarias inmediatas y pagos con QR). -Estas situaciones vienen siendo atendidas de manera conjunta por Novatronic, Temenos y el Banco de la Nación. 03/06/2025: Según la información enviada de Planeamiento mediante correo respecto al proyecto en el mes de abril se tiene que: Durante las pruebas integrales (participación de los 3 proveedores) se presentó incidencias con el tarifario dinámico que interactúa con todo el proceso de interoperabilidad (transferencias interbancarias inmediatas, pago con QR) la que está siendo atendidas por Novatronic. Asimismo, el proveedor Tenemos, presentó incidente en la data que se trasmite al core T24. Se realizan reuniones de seguimiento 2 veces al día para el seguimiento de las pruebas y corrección de los incidentes Se estima culminar las pruebas en desarrollo la primera semana de mayo iniciar pruebas en el ambiente de Calidad. 07/05/2025: Según la información enviada por Planeamiento mediante correo: Se continúan las pruebas en desarrollo de las funcionalidades de transferencias inmediatas, por contacto y QR con el proveedor BACKBASE, TEMENOS y NOVATRONIC. Se mantienen las pruebas en desarrollo de las funcionalidades de retiro y deposito en agente BN y para retiro y depósito en ventanilla con el proveedor TEMENOS y el BN. 31/12/2024: Las áreas usuarias validaron las funcionalidades de retiro y depósito en Ventanilla y se procedió con la generación del Anexo 2 para solicitar la inscripción en el Clear Quest. Se continúan coordinando con el proveedor Temenos para correcciones. Siguen en construcción la funcionalidad de transferencias Q 23/05/24 Mediante comité estratégico de proyectos con fecha 06.05.24 se aprobó el control de cambios del proyecto.Esto implica nuevas actividades y actualizacion en el cronograma. TI solicitará al usuario remtiir anexo 1 actualizado. 08/04/24 Se cambió la fecha de Fin de proyecto a 2025 20/03/24 Usuario remitió modelo de negocio y se registró en la demanda estrategica de TI, sin embargo se encuentra pendiente que el usuario remita modelo de negocio actualizado. Está retrasado porque el proveedor no contempló dentro del cronograma actividades funcionales que son necesarias para el proytecto. Presentarán un control de cambios a nivel de alcance, tiempo y presupuesto.
A10: 8 | B10: PROGRO-EO08-23-12 | C10: Servicio de Implementación y Licenciamiento de un Software para la Gestión del Riesgo Operacional, Seguridad de la Información y Continuidad del Negocio para el BN | D10: Fortalecer la Gestión de Riesgo Operacional, Seguridad de la Información y Continuidad del Negocio del Banco de la Nación | E10: Riesgos | F10: Victoria Galvez | G10: Diana Mogollon | H10: Rina Roca | I10: 1884223 | M10: 45121 | N10: Acta Nº8-2023 | O10: Tecnológica | P10: Gestión Interna | Q10: 2023 | R10: 2025 | S10: 3 | T10: Si | U10: Sí | V10: Riesgo Operacional | W10: Si | X10: Jorge Mora | Y10: 45110 | Z10: 46052 | AA10: 0.97 | AB10: 0.97 | AC10: =Tabla3[[#This Row],[% Avance ejecutado]]-Tabla3[[#This Row],[% Avance Planificado]]/Tabla3[[#This Row],[% Avance Planificado]] -> -0.03 | AD10: 02. En Curso | AE10: 14/04/2026: En el mes de marzo, al cierre se realizó el pase al ambiente de Certificación tras pruebas de usuario e integración, identificándose cinco (5) casos de prueba con observaciones y dos (2) vulnerabilidades de severidad media, a ser subsanadas por el proveedor en la actualización del 30.04.2026; asimismo, se presentaron inconvenientes en la gestión de accesos al servidor IVANTI para Achiwan (Telefónica Tech) y Clarity (prov. Ivanti), generando demoras en el inicio de pruebas de integración en Desarrollo, situación que a la fecha se encuentra superada para continuar con el pase a calidad. 23/03/2026: En febrero se actualizó la herramienta para corregir observaciones y vulnerabilidades detectadas en Calidad; un nuevo escaneo identificó dos vulnerabilidades medias, ya comunicadas al proveedor para su remediación. Además, se iniciaron pruebas de usuario con TI y las gestiones para la solicitud de cambios del proyecto. 20/03/2026: Según el acta de reunión del comité de proyectos del mes de enero, el proyecto marchó de acuerdo a lo planificado al cierre de diciembre 2025. En enero 2026 se efectuó el pase al ambiente de Certificación. Sin embargo, el proyecto ha presentado demoras en la actividad "Despliegue en calidad" debido a inconvenientes en el despliegue de la aplicación Global Suite y a problemas en la carga de datos en el servidor, lo cual puede impactar en la culminación del proyecto en enero 2026. 25/02/2026: Durante el proceso de Certificación del BN se identificaron vulnerabilidades, por lo que TI–Seguridad solicitó al proveedor su subsanación como condición para el pase a producción. La herramienta fue actualizada, pero no se corrigieron todas las vulnerabilidades. Posteriormente, en las pruebas de calidad y usuario, se detectaron nuevos errores funcionales y la reaparición de errores ya subsanados, los cuales fueron remitidos al proveedor y continúan pendientes de corrección; en consecuencia, se formulará una solicitud de cambio. 21/01/2026: Al 12.12.2025 se concluyeron los entregables hasta el E10 y se realizó el pase a Certificación. El E11 (Proceso de Certificación del BN) presenta demoras en “Despliegue en Calidad” por inconvenientes en GlobalSuite y en la carga de data del ETL, los cuales vienen siendo subsanados. Es necesario culminar el E11 para iniciar las pruebas de calidad y usuario, para lo cual se vienen coordinando reuniones adicionales. En el levantamiento de vulnerabilidades se identificaron 6 vulnerabilidades medias: 5 falsos positivos y 1 vulnerabilidad pendiente (CSP: Directiva Wildcard), con fecha comprometida 11.01.2026. 30/11/2025: Se logró el cierre del entregable 6 "Parametrizacion del modulo Administracion" y del entregable 8 "Parametrizacion del módulo de seguridad de la informacion". Con respecto al entregable 7 "Parametrizacion del modulo de Riesgo Operacional" en la actividad de configuracion de reportes, hubo observaciones funcionales en la reporteria que esta generando demoras en la implementacion del entregable, por lo que el proveedor se encuentra subsanando las observaciones para la primera semana de diciembre se estima su conclusión. En el entregable 10 "Pruebas en ambiente de desarrollo", en la actividad analisis de vulnerabilidades, el area de la Seguridad de la informacion realizo escaneos y encontro vulnerabilidades que estan pendientes de subsanar por parte del proveedor." 31/10/2025: Según la información enviada de Planeamiento en el mes de Octubre se precisa lo siguiente: "Al 31.10.2025, se efectuaron las siguientes actividades del entregable ""Instalación, configuración e integracion de la solución"" en el amibiente de desarrollo: 1. Iimplementacion de la reporteria BI.(10/02/2025). Concluido al 100% 2. Integración IBM -ISIM con la herrramienta GlobalSuite( 10/02/2025). Concluido al 100% Asimismo, se elaboró los documentos para la solicitud de cambio con la actualización del cronograma coordinado con la Gerencia de TI." 30/09/2025: Según la información enviada de Planeamiento en el mes de Septiembre se precisa lo siguiente: En cuanto a la Implementación de la Reporteria BI (dentro del Entregable 5), se solucionó la habilitación de servidor y actualmente el proveedor está configurando el servidor con los componentes necesarios para la reportería. Con respecto a la Integración ISIM ( dentro del Entregable 5), el proveedor Telefonica Tech, con apoyo de un proveedor local especializado, ha desarrollado el conector para la integración ISIM y actualmente se encuentra en proceso de configuración para integrar los perfiles requeridos para la herramienta GlosbSuite. 16/09/2025:Según la información enviada de Planeamiento en el mes de Agosto se precisa lo siguiente: A la fecha; la solicitud de ampliación de los plazos solicitada por el proveedor fue evaluada por el área de Logística y Legal, previos informes de la Subgerencia de Riesgos de Operación y Tecnología, concluyendo que no procede la ampliación por lo que se aplicaría las penalidades previa conformidad del área usuaria. Asimismo, continúan las coordinaciones con la Gerencia de TI para la habilitación de (01) servidor y (01) Instancia de base datos al proveedor para la generación de reportería BI. Asimismo, se viene elaborando cronograma considerando nuevos plazos con fecha fin estimada de proyecto (dic 2025). Se procederá a la presentación de la solicitud de cambios en el próximo comité de proyectos. 21/08/2025: De acuerdo al Acta de Comité de Proyectos del 14/08 N°07-2025 se informa que: Se solicita a la Gerencia de Riesgos realizar un informe situacional del proyecto y formalizar su solicitud de cambio para el próximo Comité Ejecutivo de Proyectos. 13/08/2025: De acuerdo al Acta de Comité de Proyectos del 16/07 N°06-2025 se informa que: El Jefe de Sección Políticas de Seguridad de Información de la Gerencia de Riesgos expuso las dificultades técnicas del proyecto. Ante ello, se solicita a la Gerencia de TI coordine y brinde el apoyo tecnológico necesario para continuar con las actividades del proyecto. Asimismo, la Gerencia de Riesgos, líder del proyecto, deberá revisar si el contrato con el proveedor define penalidades por incumplimiento y deberá remitir el calendario actualizado luego de su gestión de ampliación con el proveedor. 18/08/25: Según la información enviada de Planeamiento en el mes de Julio se precisa lo siguiente: Se continúa con el proceso de implementación de las funcionalidades de los módulos de Administración, Riesgo Operacional, Seguridad de la Información y Continuidad de Negocio. Sin embargo, no se concluyó con la fecha fin del proyecto planificada debido principalmente a la demora en la implementación de la reportería BI - (40) (Bussines Inteligent) por parte del proveedor y de la alta dependencia del fabricante del software (GlobalSuite). En ese sentido, el proveedor remitió carta (31.07.25) comunicando la necesidad de solicitar la ampliación de los plazos establecidos en el contrato. A la fecha, el área líder el proyecto viene elaborando la solicitud al proveedor del nuevo cronograma y a su vez coordinando la solicitud de la habilitación de (02) servidores (base de datos y ETL-Extracción de Información, transformación y carga de datos a la Gerencia de TI . 18/07/2025: Se continúa avanzando el proceso de implementación de las funcionalidades de los módulos de Administración, Riesgo Operacional, Seguridad de la Información y Continuidad de Negocio; que han presentado demoras por parte del proveedor por la alta dependencia del fabricante del software. Se han finalizado las integraciones a Oracle, Ivanti, Directorio Activo y alertas a los correos. Telefónica Techh se encuentra desarrollando el conector ISIM-Globalsuite e implementación de la reportería por módulos. Esta pendiente remitir la carta al proveedor por los retrasos de los compromisos del proyecto. 11/06/2025:Según la información enviada de Planeamiento en el mes de Mayo se precisa lo siguiente: Hay retrasos en las tareas de reportería, conector ISIM, pruebas, etc., Estos se deben a la alta dependencia de Telefónica con su partner Global Suite. En abril se reporto avance de 43%, proyecto tiene fecha de fin julio 2025. 03/06/2025: Según la información enviada de Planeamiento mediante correo respecto al proyecto en el mes de abril se tiene que: Los retrasos en las tareas como reportería, conectores ISIM, etc., se deben a la dependencia de Telefónica con su partner GlobalSuite. Adicionalmente, la limitada flexibilidad del proveedor para ofrecer alternativas a los impases está generando demoras en los ajustes y aprobaciones del área de riesgo 07/05/2025: Según la información remitida por Planeamiento mediante correo: Se han completado 4 de los 15 entregables. El quinto está retrasado por incumplimientos de Global Suite. Por lo que se espera sean superadas en abril. 31/12/2024: Esta en ejecución las tareas: Instalación, Parametrización, Conversión y Migración que tienen retrasos de hasta 7 meses ,debido a las integraciones con las Aplicaciones IVANTI y Oracle y las pruebas de los módulos nuevos con los usuarios. 22/05/24 Usuario presentará un control de cambios; confirman que culminan este año 2024. Contrato firmado el 15/05/24, revisar Memo 086-2024/2182 donde solicitan apoyo de TI.AO24 03/05/2024 En proceso logístico para el otorgamiento de Buena pro 08/04/24 Se ha cambiado la fecha de Fin de proyecto de 2025 a 2024. 20/03/24 Está retrasado en la suscripcion del contrato. Se agendará una reunión para revisar las siguientes actividades que involucra a TI según cronograma. Pendiente que el usuario remita modelo de negocio para registrar el Proyecto en la demanda estrategica priorizada. Pendiente envío Modelo de Negocio
A11: 9 | B11: PROPLAFT-EO08-23-13 | C11: Implementación de la Solución tecnológica para la prevención de fraudes, lavado de activos y del financiamiento del terrorismo (LA/FT) y aplicación de scoring de riesgos de LA/FT | D11: El proyecto que inició el 19.03.2021, consiste en implementar una solución tecnológica conformada por hardware (opcional), Software, Capacitación o entrenamiento y Servicios orientada a monitorear transacciones sospechosas a fin de prevenir y/o detectar oportunamente operaciones fraudulentas y/o de presunto lavado de activos y financiamiento del terrorismo en el Banco de la Nación (en adelante BN) a nivel Nacional. | E11: Riesgos | F11: Victoria Galvez | G11: Luis Garcia; Liliana Casafranca | H11: Maria Isabel Elguera | I11: 11876435 | M11: 45121 | N11: Acta Nº8-2023 | O11: Tecnológica | P11: De cara al ciudadano | Q11: 2021 | R11: 2025 | S11: 3 | T11: Si | U11: Sí | V11: Sentinel | W11: Si | X11: Jorge Ruiz | Y11: 44274 | Z11: 46160 | AC11: =Tabla3[[#This Row],[% Avance ejecutado]]-Tabla3[[#This Row],[% Avance Planificado]]/Tabla3[[#This Row],[% Avance Planificado]] -> #DIV/0! | AD11: 02. En Curso | AE11: 14/04/2026: En el mes de marzo, respecto al Entregable 9 se realizó la integración con los canales ATM, AGENTE y VISA; y respecto al Entregable 12 se inició la actualización del perfil transaccional, la cual culminará a principios de junio de 2026. 23/03/2026: Para el cierre de febrero, se viene coordinando con el proveedor la entrega del cronograma detallado de actividades, en el cual se evidencian los porcentajes de avance. Se estima contar con dicha información en marzo. 20/03/2026: Según el acta de reunión del comité de proyectos del mes de enero, el proyecto presentó un ligero retraso al cierre de diciembre 2025, no logrando culminar la implementación de los 03 procesos planificados para el 2025, debido a que no se tenía la información homologada. La Gerencia de Operaciones señaló que espera culminar con las pruebas pendientes a fines de enero 2026. 25/02/2026: En enero no se registraron nuevos entregables en producción; no obstante, se avanzó en actividades de los Entregables 7 y 9. Asimismo, se viene coordinando con el Consorcio la actualización de fechas de compromiso para las próximas salidas a producción de los Entregables 7, 9 y 12, estimándose contar con un cronograma consensuado la próxima semana 21/01/2026: Finalización de pruebas de Modelos basados en Reglas; redacción y conformidad de actas de pruebas en Desarrollo y Certificación; gestiones para la reducción de la prestación del Canal Banca Celular; aceptación y cierre del Entregable N°10 (pase a producción 10.12.2025); validación post-producción de Reglas en App Móvil y HomeBanking.La culminación del Entregable N°11 depende de la culminación del Entregable N°9, dado que el informe de avance comprende los entregables 9 y 10. 30/11/2025: En noviembre se efectuó el pase a producción correspondiente a la parte funcional de la herramienta (fase 1) correspondiente al Proyecto Sentinel. Durante diciembre se completará el pase a producción de la fase 2, lo que permitiría considerar el entregable 10 como finalizado al 100%. No obstante, al cierre de noviembre ningún entregable posterior al número 6 alcanza el 100% de avance. A la fecha el proyecto es medido a nivel entregables debido a que no han compartido el cronograma detallado del proyecto. 31/10/2025: Según la información enviada de Planeamiento en el mes de Octubre se precisa lo siguiente: Su nivel de avance es a nivel entregables ya que no se cuenta con un cronograma detallado. Asimismo, está presentado una solicitud de cambio donde el proyecto culminaría en Mayo 2026. 30/09/2025: Según la información enviada de Planeamiento en el mes de Septiembre se precisa lo siguiente: La gerencia de riesgos en coordinación con la gerencia de TI ha elaborado un nuevo cronograma a fin de que el proveedor lo revise y de la conformidad. Dicho cronograma acompañado de un informe por la gerencia de riesgos fue presentado al Directorio. Ante ello, la sesión de Directorio ha determinado que se brindará lo necesario para acotar los plazos. 16/09/2025:Según la información enviada de Planeamiento en el mes de Agosto se precisa lo siguiente: La gerencia de Riesgos no ha reportado % de avance en el mes de agosto 2025. 21/08/2025: De acuerdo al Acta de Comité de Proyectos del 14/08 N°07-2025 se informa que: Se solicita a la Gerencia de Riesgos realizar un informe situacional del proyecto y formalizar su solicitud de cambio para el próximo Comité Ejecutivo de Proyectos. 18/08/25: Según la información enviada de Planeamiento en el mes de Julio se precisa lo siguiente: - Hay Entregables vencidos (6 de 12) - Cronograma desactualizado (fecha fin: Junio 2025) - La gerencia líder del proyecto no reporta información del estado del proyecto. 13/08/2025: De acuerdo al Acta de Comité de Proyectos del 16/07 N°06-2025 se informa que: No presentaron reporte al cierre de junio a la Sub Gerencia de Planeamiento. Sin embargo, se está efectuando reuniones semanales entre las gerencias participantes y la Gerencia General para monitorear у tomar decisiones en conjunto respecto a actividades propias del BN, así como coordinar actividades con el proveedor. 18/07/2025: Se tuvo una reunión el 16.06.2025 entre las gerencias de TI, gerencia de Riesgos, OPLAFT y Planeamiento. Se expuso que el cronograma que se envió al proveedor no ha sido aceptado debido a que no comtempla las fechas solicitadas para finalizar el 2025. Por otro lado, las áreas usuarias contemplan que hay data que trabajar para poder darsela al proveedor y cumplir con las actividades planificadas. Por otro lado, va a ver una reunión con legal para ver temas contractuales con el proveedor. 11/06/2025:Según la información enviada de Planeamiento en el mes de Mayo se precisa lo siguiente: Entregable 7 Fase 2 Ambiente de Desarrollo continúan las pruebas de perfiles ,funcionales y la validación de Calidad de datos de los archivos de 5 días, en paralelo se están generando desde 2/5 los archivos de 6 meses con los programas extractores v2 . Entregable 9 se culmino la integración de datos desde los canales en el ambiente Desarrollo. Entregable 10 se culmino las pruebas en el ambiente de Certificación esta en proceso la firma de los IRPF y RC . 03/06/2025: Según la información enviada de Planeamiento mediante correo respecto al proyecto en el mes de abril se tiene que: Se encuentra en actualización el Cronograma entre el BN y SS el cual generara la versión 3. Se desplego la versión 7.12.1 de Sentinel Core y Predictions en el ambiente de desarrollo. 07/05/2025: Según la información remitida por Planeamiento mediante correo: Se esta desplegando la nueva versión de Sentinel Core y Predictions que resuelve issues identificadas durante las pruebas hasta dic 2024. Entregable 7 La revisión de Calidad de datos no se esta cumpliendo en fecha debido a la que la información aun sigue siendo corregida por parte de TI-BN , existe una alta dependencia de un solo especialista para el análisis y construcción de los programas extractores . Entregable 9 Hay retraso en el inicio de las pruebas funcionales en el ambiente de desarrollo debido a las actividades previas por parte de TI-BN y Smartsoft. Entregable 10 Aún están pendientes de firma las RC , ya que dependen de los IRPF, tanto de Producto como Funcional, los cuales no han sido remitidos con las firmas correspondientes por parte de Smartsoft. Una vez que Smartsoft entregue los IRPF debidamente visados, los usuarios y el equipo de TI - BN procederán con el visado final para su cierre. 31/12/2024: A nivel entregables se encuentran en ejecución 4 entregables. OPLAFT El entregable 7 se encuentra a un 86 %. Se culmino la certificación de la Fase 1 (Productos y Perfiles). Fraudes El entregable 9 se encuentra a un 70 %. Se definió el tema de las pruebas RT y NRT . El entregable 10 se encuentra a un 65 %. El entregable 12 se encuentra a un 92 % Se culmino la certificación. 23/05/2024 Mediante Comité Estratégico de proyectos de fecha 06.05.24 se informa la aprobación de control de cambios del proyecto 08/04/24 Se ha cambiado la fecha de inicio de proyecto de 2023 a 2021 20/03/24 TI compartirá con Planeamiento el nuevo plan actualizado para que se gestione el control de cambios con el Líder del Proyecto.
A12: 10 | B12: PROASL-EO10-23-18 | C12: Adquisición de Switches Lan para las sedes Administrativas y dependencias del BN | D12: Renovar los equipos de comunicaciones que brindan el acceso a la red del banco a los usuarios administrativos y de las dependencias como Agencias, Lobbys y Oficinas especiales, usando protocolos de seguridad y acceso actualizados y estándares en la industria de Tl. | E12: Tecnologías de Información | F12: Alejandro Sifuentes | G12: - | H12: No definido | I12: 7584500 | J12: =Tabla3[[#This Row],[Presupuesto asignado]]/2 -> 3792250 | K12: =Tabla3[[#This Row],[Valor Ganado (EV)]] -> 3792250 | L12: =Tabla3[[#This Row],[Valor Ganado (EV)]]/Tabla3[[#This Row],[Costo Actual (AC)]] -> 1 | M12: 45121 | N12: Acta Nº8-2023 | O12: Tecnológica | P12: De cara al ciudadano | Q12: 2023 | R12: 2025 | S12: 0 | T12: Si | U12: Sí | V12: Switches LAN | W12: Si | X12: Erick Romero | Y12: 44928 | Z12: 45774 | AA12: 1 | AB12: 1 | AC12: =Tabla3[[#This Row],[% Avance ejecutado]]-Tabla3[[#This Row],[% Avance Planificado]]/Tabla3[[#This Row],[% Avance Planificado]] -> 0 | AD12: 03. Implementado | AE12: IMPLEMENTADO 11/06/2025:Según la información enviada de Planeamiento en el mes de Mayo se precisa lo siguiente: El Equipo Técnico del proyecto informó que, se culminó con la implementación al 100%. Asimismo, se presentó el avance de las siguientes actividades: Implementación: Ejecución: 100% (finalizado) Monitoreo y Control: 100% (finalizado) Cierre 100% (finalizado) 03/06/2025: Según la información enviada de Planeamiento mediante correo respecto al proyecto en el mes de abril se tiene que: El proyecto ha sido culminado. Fin del Proyecto. 21/05/2025: Según el Acta de Reunión N°04-2025 del Comité de Proyectos, se enviará a Planeamiento el Acta de Cierre del Proyecto y el fomato de lecciones aprendidas en las próximas semanas. 07/05/2025: Según la información remitida por Planeamiento mediante correo: A nivel tareas, actualmente se encuentra en la Etapa de Implementación del Proyecto. El Equipo Técnico del proyecto informó que, solo faltan instalar 45 equipos de 547 nuevos equipos en la Red de Agencias. Además, se revisaron posibles riesgos y desafíos que podrían impactar el cronograma, con el objetivo de tomar medidas preventivas y correctivas. Finalmente, se comunicó que las actividades del proyecto se vienen realizando de acuerdo a lo planificado. Asimismo, se presentó el avance de las siguientes actividades: • Implementación: Ejecución: 96% (en proceso) Monitoreo y Control: 97% (casi finalizado) 31/12/2024: *Se instalaron 280 switches para las sedes administrativas así como la implementación de los servidores plataforma de gestión, la solución NAC y Control de accesos. Dado esto, se viene realizando la entrega de la conformidad del servicio para el pago correspondiente por esta primera etapa. * Los usuarios de Canales Virtuales y Red de Agencias solicitaron no realizar trabajos durante esta semana por lo que se suspenden las actividades hasta el mes de enero. 23/05/24 Validar si se firmó el contrato. A espera que el proveedor entregue el plan de trabajo. 25/04/2024 Mediante Memo N° 63-2024-BN2810 en que se entrega la nueva lista de proyectos con componente TI se genera cambio en el lider del proyecto de José Macedo a Alejandro Sifuentes 25/04/2024 Mediante Memo N°60-2024-BN2810 se informa que se requiere el informe de las razones del retraso del proyecto asi como sus acciones correctivas para la presentación al comité del 26.04 20/03/24 Esta en proceso logistico (analisis de oferta y la buena pro se dará en marzo). Presentarán un nuevo cronograma con control de cambios.
A13: 11 | B13: PROGSE-EO10-23-19 | C13: Adquisición de Solución de Granja de Servidores Empresariales | D13: Renovar y ampliar los recursos de infraestructura de servidores con los que cuenta el Banco, garantizando su continuidad, disponibilidad y la mejora de su rendimiento operativo. Asimismo, la de soportar/operar toda la carga operacional de los servidores en cada uno de los Centros de Cómputo del Banco de forma independiente, considerando también cubrir la demanda de crecimiento futuro de servidores requeridos por nuestra institución. | E13: Tecnologías de Información | F13: Alejandro Sifuentes | G13: - | H13: No definido | I13: 7000000 | J13: =Tabla3[[#This Row],[Presupuesto asignado]]/2 -> 3500000 | K13: =Tabla3[[#This Row],[Valor Ganado (EV)]] -> 3500000 | L13: =Tabla3[[#This Row],[Valor Ganado (EV)]]/Tabla3[[#This Row],[Costo Actual (AC)]] -> 1 | M13: 45121 | O13: Tecnológica | P13: De cara al ciudadano | Q13: 2023 | R13: 2024 | T13: Si | U13: Si | V13: Granja | W13: No | X13: Edward Torres | Y13: 44957 | Z13: 45499 | AA13: 1 | AB13: 1 | AC13: =Tabla3[[#This Row],[% Avance ejecutado]]-Tabla3[[#This Row],[% Avance Planificado]]/Tabla3[[#This Row],[% Avance Planificado]] -> 0 | AD13: 03. Implementado | AE13: IMPLEMENTADO 23/05/24 Validar si ya se dió la buena Pro. 25/04/2024 Mediante Memo N°60-2024-BN2810 se informa que se requiere el informe de las razones del retraso del proyecto asi como sus acciones correctivas para la presentación al comité del 26.04 20/03/24 Esta en proceso logistico y la buena pro se dará en marzo. Presentarán un nuevo cronograma con control de cambios.
A14: 12 | B14: ID N° | C14: Multired Empresarial - Fase III | D14: Modernizar y agilizar el proceso de pagos del Estado, permitiendo realizar transacciones y gestiones de manera electrónica, eliminando la necesidad de trámites presenciales. | E14: Operaciones | F14: Jorge Lavalle | G14: - | H14: No definido | I14: 0 | J14: =Tabla3[[#This Row],[Presupuesto asignado]]/2 -> 0 | K14: =Tabla3[[#This Row],[Valor Ganado (EV)]] -> 0 | L14: =Tabla3[[#This Row],[Valor Ganado (EV)]]/Tabla3[[#This Row],[Costo Actual (AC)]] -> #DIV/0! | M14: 45121 | O14: Procesos Digitales | P14: De cara al ciudadano | Q14: 2023 | R14: 2024 | T14: Si | U14: Si | V14: Multired empresarial | W14: Sí | X14: Eduardo Cárdenas | Y14: 45208 | Z14: 45401 | AA14: 1 | AB14: 1 | AC14: =Tabla3[[#This Row],[% Avance ejecutado]]-Tabla3[[#This Row],[% Avance Planificado]]/Tabla3[[#This Row],[% Avance Planificado]] -> 0 | AD14: 03. Implementado | AE14: IMPLEMENTADO 23/05/24 Validar que estan al 25% de desplieuge en Calidad. Presentarán un control de cambios. 08/04/24 Se ha cambiado la fecha de Fin de proyecto al 2024 21/03/24 Se coordinará con el usuario - Marco Ortiz, para tratar el requerimiento como una mejora, mas no como un proyecto. En febrero culminaron el desarrollo y pruebas con el usuario. TI validará si ya se encuentra en calidad. Pendiente que el usuario remita modelo de negocio para registrar el Proyecto en la demanda estrategica priorizada.
A15: 13 | B15: ID N° | C15: Servicio Levantamiento Secreto Bancario | D15: Actualmente se brinda el servicio Levantamiento del Secreto Bancario, el cual atiende al Poder Judicial principalmente. Dicho servicio para su atención, requiere de información transversal que proviene de distintas áreas del Banco y son consolidadas por la Sección Depositos Judiciales. Las actividades de cada uno de los distintos procesos son atendidos de manera manual y de forma repetitiva, los cuales conllevan a riesgos de error operativo y posibles pérdidas económicas. La solución busca Optimizar la eficiencia de los procesos (OEI 8), mediante la automatización del proceso lo que incidirá en la Mejorar la experiencia del Cliente (OEI 4), los que se medirán en la disminución de los tiempos de atención conforme a cada proceso automatizado, y reducir el riesgo de multas y demandas al BN. | E15: Operaciones | F15: Carla Figallo | G15: Andrea Peve | H15: No definido | I15: 101600 | J15: =Tabla3[[#This Row],[Presupuesto asignado]]/2 -> 50800 | K15: =Tabla3[[#This Row],[Valor Ganado (EV)]] -> 50800 | L15: =Tabla3[[#This Row],[Valor Ganado (EV)]]/Tabla3[[#This Row],[Costo Actual (AC)]] -> 1 | M15: 45121 | O15: Procesos Digitales | P15: De cara al ciudadano | Q15: 2023 | R15: 2024 | T15: Si | U15: Si | V15: Secreto bancario | W15: Sí | X15: Darwin Valenzuela | Y15: 45040 | Z15: 45510 | AA15: 0.44 | AB15: 0.4 | AC15: =Tabla3[[#This Row],[% Avance ejecutado]]-Tabla3[[#This Row],[% Avance Planificado]]/Tabla3[[#This Row],[% Avance Planificado]] -> -0.6 | AD15: 04. Cerrado | AE15: 05/07/24 Mediante MEMORANDO N° 00000197 - 2024-BN/3212 la usuaria remite anexo 1 actualizado. 27/06/24 Usuario remitió Anexo 2 actualizados mediante MEMORANDO N° 00000195 - 2024-BN/3212 de fecha 27/06, que son asociados al proyecto. 23/05/24 Validar que el contrato esté firmado. Pendiente envio de la Solicitud de Cambio a Planeamiento. 10/05/2024 A la espera del anexo 1 actualizado para redimensionar el alcance del proyecto, memo 0008-2024-BN-2542 19/04/2024 Por correo remitido por Junior Quicano se da respuesta a las consultas y observaciones homologadas por parte de TI, en el documento excelse hace mención que exsiten algunas consultas que deben ser correspondidas por el Área Usuario, para otras consultas el BN brindará servicio VPN, asi mismo, hay respuestas que fueron realizadas en las consultas de TDR 17/04/2024 Mediante correo remitido por Martin Nicho se hace llegar las observaciones y consultas de BellTech y Mora Technology se pide apoyo para la solventación de las mismas por parte de las subgerencias de TI, Arquitectura de datos, Seguridad Informática, Soporte de infraestructura, Usuario y Logística. 21/03/2024 Usuario remitió modelo de negocio y se registró en la demanda estrategica de TI. Usuario se encuentra en proceso logísitico. Comentar que en la demanda táctica existen 02 requerimientos asociados, del cual se ha recomendado al usuario incluir dentro del alcance del Proyecto, para ello se solicita a Planeamiento agendar reunión con Area usuaria y TI para definir el tratamiento del mismo.
A16: 14 | B16: ID N° | C16: Implementación del servicio de Inmediatas e Interoperabilidad (Transferencias Inmediatas e Interoperabilidad) | D16: Asegurar el restablecimiento del servicio de Transferencias Interbancarias Inmediatas a través del sistema de la Cámara de Compensación Electrónica (CCE). Además, se busca habilitar las funcionalidades de Interoperabilidad necesarias según las exigencias del Banco Central de Reserva del Perú (BCRP). | E16: Operaciones | F16: Jorge Lavalle | G16: - | H16: No definido | I16: 384787 | J16: =Tabla3[[#This Row],[Presupuesto asignado]]/2 -> 192393.5 | K16: =Tabla3[[#This Row],[Valor Ganado (EV)]] -> 192393.5 | L16: =Tabla3[[#This Row],[Valor Ganado (EV)]]/Tabla3[[#This Row],[Costo Actual (AC)]] -> 1 | M16: 45121 | O16: Servicio a los Clientes | P16: De cara al ciudadano | Q16: 2022 | R16: 2024 | T16: Si | U16: Si | V16: Transferencia inmediata | W16: Sí | X16: Mario Carbajo | Y16: 44866 | Z16: 45322 | AA16: 1 | AB16: 1 | AC16: =Tabla3[[#This Row],[% Avance ejecutado]]-Tabla3[[#This Row],[% Avance Planificado]]/Tabla3[[#This Row],[% Avance Planificado]] -> 0 | AD16: 03. Implementado | AE16: IMPLEMENTADO 08/04/24 Se han cambiado las fechas de Inicio y Fin de proyecto 2023-2023 a 2022-2024 21/3/2024 Usuario está realizando un control de cambios para quitar la actividad de la implementación de la modalidad de QR dentro del Proyecto. Esta SC se expondrá en el proximo comité para su aprobación y para la formalización del cierre del proyecto.
A17: 15 | B17: PRORPA-EO08-23-27 | C17: Implementación del Proyecto de Robotización (Automatización de Procesos - RPA) | D17: El uso de estas herramientas tecnológicas permitirá digitalizar servicios de cara a los principales grupos de interés, en ese sentido con la finalidad de optimizar la eficiencia de los procesos se ha visto por conveniente la implantación de sistemas automatizados mediante robots, para lo cual se ha identificado la necesidad de automatizar actividades manuales y repetitivas en 10 procesos de servicios que brinda el Banco. | E17: Operaciones | F17: María Luisa Guevara | G17: Marco Ortiz; Andrea Peve | H17: Rina Roca | I17: 2166000 | M17: 45121 | N17: Acta Nº8-2023 | O17: Procesos Digitales | P17: Gestión Interna | Q17: 2023 | R17: 2025 | S17: 3 | T17: Si | U17: Sí | V17: Robotización | W17: Si | X17: Elia Muñoz | Y17: 45048 | Z17: 46052 | AA17: 1 | AB17: 1 | AC17: =Tabla3[[#This Row],[% Avance ejecutado]]-Tabla3[[#This Row],[% Avance Planificado]]/Tabla3[[#This Row],[% Avance Planificado]] -> 0 | AD17: 03. Implementado | AE17: 23/03/2026: Para el cierre de febrero, se culminó con los 10 procesos satisfactoriamente logrando pasar a producción en febrero 2026. En consecuencia, se solicita se cierre el proyecto Servicio de suscripción de licencia de software para la automatización robótica de procesos (RPA). Se formalizó con la remisión del acta de cierre y el anexo de lecciones aprendidas del proyecto. 20/03/2026: Según el acta de reunión del comité de proyectos del mes de enero, el proyecto presentó un ligero retraso al cierre de diciembre 2025, no logrando culminar la implementación de los 03 procesos planificados para el 2025, debido a que no se tenía la información homologada. La Gerencia de Operaciones señaló que espera culminar con las pruebas pendientes a fines de enero 2026. 25/02/2026: Se realizó la consistencia del proceso de cheques efectuándose las pruebas correspondientes entre el área usuaria y TI, se está preparando la documentación para el pase a calidad y despliegue en producción en la 2da. semana de febrero. En consecuencia, se procederá a la elaboración de la documentación para el cierre del proyecto. 21/01/2026: Respecto a la actividad E6, de los tres procesos se encuentra desplegado Tarjeta de Crédito hipotecario y Carta Fianza. Para Préstamo Multired, el área usuaria generó los perfiles y se viene solicitando a Seguridad Informática la creación de credenciales del robot, con despliegue a producción planificado para el 09/01/2026. Asimismo, el proceso de consistencia de cheques presenta dificultades en pruebas; se han programado pruebas entre el área usuaria y TI para el 08/01/2026, a fin de culminar y pasar a Calidad. 30/11/2025. AL cierre de noviembre, se concluyó las pruebas en desarrollo de los 03 procesos Préstamo Multired y Tarjetas, Crédito hipotecario y Cartas Fianza, Cargado y consistencia de canje de entrada (cheques). Asimismo, con respecto al pase certificación se están realizando las coordinaciones con la Gerencia de Productos e Inclusión Financiera - GPIF (usuario) y con la Subgerencia de Seguridad informática para validar los formatos de acceso (roles usuario) se estima contar con los permisos de acceso para la 1ra semana de diciembre y continuar con las pruebas en certificación y el pase a producción según lo planificado para el mes próximo. 31/10/2025: Según la información enviada de Planeamiento en el mes de Octubre se precisa lo siguiente: "Al 31.10.2025, con la participación del proveedor Belltech y usuarios del Banco (Operaciones y TI), se ha concluido con la certificación del 2° entregable 02 y se encuentra en marcha blanca (Procesos de Levantamiento de Secreto Bancario): 1.- Atención de solicitudes, 2.- Certificados judiciales, 3.- Información ATM y 4.- Agentes Corresponsales. Referente al entregable 3, se encuentra en desarrollo y reuniones de entendimiento entre el proveedor y los respectivos usuarios de los 3 procesos que la componen: 1.- Consistencia de canje de entrada (cheques), 2.- Préstamos multired y tarjetas (Levantamiento de Secreto Bancario) y 3.- Hipotecario y Cartas Fianzas (Levantamiento de Secreto Bancario). Asimismo, se elaboró los documentos para la solicitud de cambios." 30/09/2025: Según la información enviada de Planeamiento en el mes de Septiembre se precisa lo siguiente: Al cierre del mes de setiembre, el área de calidad se encuentra documentando la certificación del entregable 02 de los 04 procesos: 1) Atención de solicitudes de secreto bancario 2) Información ATM, 3) Agentes corresponsales y 4) Certificado de depósitos judiciales; con fecha estimada del pase a producción 2da semana de octubre. Asimismo, el proveedor viene desarrollando los procesos del entregable 03, solicitando data de pruebas: 1)Préstamo multired, 2)Hipotecario y 3)Consistencia de canje de entrada (cheques). Considerar, que los plazos se encuentran desfasados, por el retraso de la atención del entregable 02, por lo que se continúa las coordinaciones con el proveedor y TI para determinar y definir el cronograma para la solicitud de cambios con ampliación de plazos. 16/09/2025:Según la información enviada de Planeamiento en el mes de Agosto se precisa lo siguiente: Al cierre del mes de agosto, en el ambiente de calidad, se encuentra en el ciclo final de pruebas de los 04 procesos: 1) Atención de solicitudes de secreto bancario 2) Información ATM, 3) Agentes corresponsales y 4) Certificado de depósitos judiciales; de los que se presentaron observaciones (incidencias en los desarrollos vinculados a OnDemand, ECAI y Host) y vienen siendo atendidas por el proveedor y el área de Calidad. Asimismo, se concluyó la generación de los perfiles de usuario para los procesos: 1)Préstamo multired, 2)Hipotecario y 3)Consistencia de canje de entrada (cheques). Sin embargo, los plazos se encuentran desfasados, por lo que se continúa las coordinaciones con el proveedor para determinar y definir el cronograma para la solicitud de cambios con ampliación de plazos (octubre 2025-fecha preliminar), el cual deberá presentarse en el mes de setiembre. 21/08/2025: De acuerdo al Acta de Comité de Proyectos del 14/08 N°07-2025 se informa que: Se solicita a la Gerencia de Operaciones realizar un informe situacional del proyecto y formalizar su solicitud de cambio para el próximo Comité Ejecutivo de Proyectos. 18/08/25: Según la información enviada de Planeamiento en el mes de Julio se precisa lo siguiente: Al cierre del mes de julio, en el ambiente de calidad, se presentaron observaciones a 03 procesos del servicio atención de solicitudes de depósitos judiciales (Información ATM, Agentes corresponsales y certificado de depósitos judiciales) lo cual fue atendido por el proveedor Belltech (31.07.25). Las observaciones mencionadas han generado retrasos en la ejecución del entregable 02 (04 Bots). En relación al entregable 03 (03 Bots), se vio afectado en la fase de desarrollo por la generación de los perfiles para los procesos préstamo multired, hipotecario y consistencia de canje de entrada (cheques). 18/07/2025: A nivel tareas: Los 04 procesos del 2do entregable se encuentran en el ambiente de Certificación Estatus de los Procesos: Proceso 13: Agentes Corresponsales (Sección Dep. Judiciales), pruebas en QA Proceso 17: Certificado de Depósitos Judiciales (Sección Dep. Judiciales), pruebas en QA Proceso 11: Atención de Solicitudes (Sección Dep. Judiciales), pruebas en QA Proceso 12: Información ATM (Sección Dep. Judiciales), pruebas en QA Se espera que para el mes de julio se culmine el entregable de los ‘4 bots y para setiembre el entregable de los 03 bots. 11/06/2025:Según la información enviada de Planeamiento en el mes de Mayo se precisa lo siguiente: Los atrasos se deben a incidencias técnicas presentadas en el proceso ATM (NCR) y de Atención a Solicitudes (perfiles y accesos). En relación a ATM´s no existe contrato vigente con NCR lo que dificulta la realización de pruebas en desarrollo. En cuanto atención de solicitudes, seguridad informática tuvo demoras en la asignación de perfiles y accesos. 03/06/2025: Según la información enviada de Planeamiento mediante correo respecto al proyecto en el mes de abril se tiene que: Debido a los inconvenientes técnicos con los que se cuenta en entorno de Desarrollo para los aplicativos de: Estados de cuenta de ahorro (ECAI) y contractuales con el proveedor NCR para Cajeros Automáticos, continúan los pendientes para pasar a entorno de certificación 2 de los 4 procesos que contempla el paquete número 02 (entregable 02). 07/05/2025: Según la información remitida por Planeamiento mediante correo: A nivel proveedor se esta avanzando con el desarrollo de los 4 bots esperando que se concreto lo que se indica en el párrafo anterior. Queda pendiente la asignación de las credenciales del journal NCR (consultas de ATM). 31/12/2024: Referente a RPA, el avance del primer entregable es de un 90%, se viene gestionando la certificación de los 3 procesos mencionados pertenecientes al primer paquete. No se contó con los requerimientos técnicos dentro de los plazos (TI) para cumplir con el hito 1 : instalación y configuración de la plataforma RPA. Por ello se presentara un control de cambios a fin de corregir y alinear el cronograma. 23/05/24 Mediante acta de comité estratégico de proyectos con fecha 06.05/24 se informa que se aprobó el control de cambios del proyecto , los usuarios deben formalizar el nuevo cronograma del proyecto y remitirlo a planeamiento. Validar que el contrato esté firmado y revisar cronograma, 1er entregable inicia el 07/06/24 (Desarrollo, QA, Producción). 03/05/2024 En proceso logístico para el otorgamiento de la Buena pro 05/04/24 Según correo remitido por MOrtiz, menciona la solicitud al área de Logística para ampliar el plazo de solución de consultas y observaciones e integración de bases del proceso de contratación. 21/03/24 Según cronograma ya estan por culminar el proceso logística. P&D agendará una reunión para revisar las siguientes actividades que involucra a TI y cuando se estarían iniciando. Pendiente que el usuario remita modelo de negocio para registrar el Proyecto en la demanda estrategica priorizada.
A18: 16 | B18: PROATM-EO05-23-3 | C18: Adquisición e instalación de 454 Cajeros Automáticos | D18: La adquisición de Cajeros Automáticos con SVCD se justifica en que requerimos reemplazar cajeros automáticos con más de 10 años de antigüedad e incrementar puntos nuevos para distribuir el volumen transaccional de algunos cajeros a nivel nacional, a fin de mantener la disponibilidad de puntos de atención a nivel nacional, descongestionando ventanillas de oficinas, descentralizando el servicio de retiros de ahorros permitiendo atención 7x24 y atender la demanda requerida para el canal ATM. | E18: Banca Digital | F18: Enrique Silva | G18: Juliana Palomino | H18: Noe Figueroa | I18: 69726960 | M18: 45121 | N18: Acta Nº8-2023 | O18: Tecnológica | P18: De cara al ciudadano | Q18: 2023 | R18: 2027 | S18: 3 | T18: Si | U18: No | V18: Cajeros Nuevos | W18: No | X18: Felix Ochoa | Y18: 45009 | Z18: 46734 | AA18: 0.56 | AB18: 0.47 | AC18: =Tabla3[[#This Row],[% Avance ejecutado]]-Tabla3[[#This Row],[% Avance Planificado]]/Tabla3[[#This Row],[% Avance Planificado]] -> -0.53 | AD18: 02. En Curso | AE18: 14/04/2026: En el mes de marzo, en reunión con la Gerencia General, Gerencia de TI y Gerencia Banca Digital, se solicitó reducir el número de internamiento a 1 y el plazo de instalación; por lo que la Gerencia de Administración y Logística quedó en confirmar la disponibilidad para recibir y almacenar los cajeros en un solo lote, así como realizar su instalación en el plazo más corto. 20/03/2026: Según el acta de reunión del comité de proyectos del mes de enero, el proyecto presentó un ligero retraso al cierre de diciembre 2025. Los documentos enviados a Logística fueron observados y deben ser subsanados y firmados nuevamente, lo que retrasa la convocatoria y todas las actividades siguientes del cronograma. Se debe revaluar la cantidad de ATMs a adquirir, reduciendo en ubicaciones con poca utilización, y evaluar alternativas de menor costo como la opción de alquiler de ATMs. 25/02/2026: Logística remitió las cotizaciones de NCR del Perú y DIEBOLD Nixdorf. Las áreas corresponsables emitieron opinión sobre la propuesta técnica, la cual fue consolidada y enviada por Banca Digital a Logística. Posteriormente, Logística informó que, conforme a la nueva Ley de Contrataciones, debían incorporarse dos cláusulas en las ETMs. Banca Digital remitió la nueva versión a la Subgerencia de Proyectos para su visto bueno, el cual se encuentra pendiente. 21/01/2026: Se ha solicitado a las áreas competentes la revisión y evaluación técnica de las cotizaciones remitidas por las empresas Diebold Nixdorf Perú S.R.L. y NCR del Perú S.A.C. El resultado de la evaluación técnica se envió el día de hoy 09/01/2026 con el memorando número 000007-3251-BN a la Gerencia de Administración y Logística. 30/09/2025: Según la información enviada de Planeamiento en el mes de Septiembre se precisa lo siguiente: Las ETMs debieron ser remitidas a la Gerencia de Logística el 7 de agosto de 2025; sin embargo, fueron enviadas el 14 de octubre de 2025. El retraso se debió al proceso de recopilación de firmas y a las modificaciones en las características de la bóveda de los cajeros pedestal, incorporadas a partir de las recomendaciones de la Subgerencia de Seguridad Física. 25/06/2025 (Omar Sarmiento) Las ETM fueron visadas y remitidas al área usuaria el martes 23 de setiembre mediante MEMORANDO N° 00000275 - 2025-BN/2541 Cabe mencionar, que desde la entrega de las ETM, se ha promovido varias reuniones de trabajo con el usuario, recibiendo modificaciones que han tenido que ser revisadas nuevamente. El último cambio realizado a las ETM por parte del usuario fue el miércoles 17 de setiembre 16/09/2025:Según la información enviada de Planeamiento en el mes de Agosto se precisa lo siguiente: El 08 de enero de 2025 se declaró la nulidad de oficio del proceso, tras lo cual fue necesario revisar diversos aspectos de su ejecución. En primer lugar, se evaluó la optimización de la red de cajeros automáticos con el fin de determinar el número adecuado de equipos a adquirir. Posteriormente, se realizaron consultas al área Legal y, luego, a la SBS para confirmar que este proceso no constituye un servicio financiero. Con esa precisión, se procedió a modificar las ETMs conforme a la nueva Ley de Contrataciones, tras lo cual el área de Logística remitió el formato actualizado en base al nuevo marco normativo. Finalmente, todas las áreas involucradas se encuentran en la elaboración de las ETMs para sustentar el estudio de mercado correspondiente. 21/08/2025: De acuerdo al Acta de Comité de Proyectos del 14/08 N°07-2025 se informa que: Se solicita a la Gerencia de Banca Digital enviar a la brevedad posible a la Gerencia de Administración y Logística los ETM's del proyecto. 18/08/25: Según la información enviada de Planeamiento en el mes de Julio se precisa lo siguiente: El proyecto presentó un control de cambio donde ahora los 454 cajeros automáticos van a ser para remplazo. 13/08/2025: De acuerdo al Acta de Comité de Proyectos del 16/07 N°06-2025 se informa que: Se aprueba la solicitud de cambio donde se cambia el nombre, el presupuesto y la fecha establecida del proyecto. Asimismo, se solicita a la Gerencia de Banca Digital reunirse con la Gerencia de TI a fin de agilizar los documentos necesarios para cerrar las ETM's y mandarlos a la Gerencia de Logística. 18/07/25: Las ETM´S se encuentran en validación de las áreas involucradas. Se espera tener respuesta para la consolidación de las ETM´s y remisión al área logística - estudio de mercado. Se espera tener la consolidación el lunes 21 de Julio. Se remitió a Planeamiento Informe de cambio de alcance en el número de ATM´s a adquirir (memorando N°235) indicando que la compra de ATM´s será en total de 454 y solo cajeros. Se ha presentado el 16.07.25 control de cambio en el alcance, presupuesto y fecha fin. 11/06/2025:Según la información enviada de Planeamiento en el mes de Mayo se precisa lo siguiente: Se esta solicitando al área de infraestructura apoyo para la logística de implementación de ATM´s El área Logística debe entregar las fechas para el nuevo cronograma en la parte de contratación. Se espera presentar la Solicitud de Cambios para el Comité de Proyectos del mes de Junio. 03/06/2025: Según la información enviada de Planeamiento mediante correo respecto al proyecto al mes de abril se tiene que: Se identificó la posibilidad de optimizar 120 cajeros mediante reubicación, y se inició la adecuación de las ETMs conforme al marco legal vigente. 21/05/2025: Según el Acta de Reunión N°04-2025 del Comité de Proyecto, se formalizará el control de cambios para el próximo comité indicando el alcance, presupuesto, tiempo y el cronograma de actividades 07/05/2025: Según la información remitida por Planeamiento mediante correo se tiene que: La SBS resuelve que la Contratación deberá convocarse por el ámbito de la Ley de Contrataciones del Estado. Asimismo, se realizó una nueva evaluación de cantidad de ATMs, el cual dio como resultado bajar el número de ATMs a 389. 28/02/25: En elaboración de ETMs como Servicio Financiero 31/01/25: TI entregó las TDR actualizadas al usuario para iniciar el proceso logístico. 31/12/2024: Con fecha 13.12.24, se reunió el Comité de Selección designado, el cual tomo por decisión unánime la pertinencia de devolver el Expediente de Contratación a efecto que se gestione la nulidad de oficio de la licitación. Con fecha 26.12.24, la LP-05-2024-BN, fue declarado con nulidad de oficio. 23/05/24 Mediante acta de comité estratégico de proyectos con fecha 06.05.24 se aprobó el control de cambios del proyecto, los usuarios deben formalizar el nuevo cronograma del proyecto y remitirlo a planeamiento. Segun crongorama en dic24 se firma el contrato. 03/05/2024 Se entregó nueva versión visada de las ETM's 25/04/2024 Mediante Memo N° 63-2024-BN2810 en que se entrega la nueva lista de proyectos con componente TI se asigna el Lider usuario al proyecto, anteriormente no contaba con uno. 19/04/2024 Mediante correo remitido por Juliana Palomina indica que la oficina de Soporte de Infraestructura Tecnológica ha respondido faltan las áreas de Construcción de aplicaciones, Canales presenciales, oficina de seguridad de información y las áreas relacionadas a la declaración Jurada 19/04/2024 Con correo remitido por Martin Nicho se hace notificar las observaciones y consultas de los proveedores Belltech y NCR, se busca respuestas de la Sección Operaciones de la Infraestructura Tecnológica, Sub gerencia de construcción de aplicaciones, Sección de canales presenciales, las áreas involucradas en el proceso de verificación física de los ATMs para la escritura de la declaración jurada en el cumplimiento de las bases, y el pronunciamiento de Seguridad de información. 20/03/24 Proyecto Nuevo. Se encuentra en proceso logistico solo la parte de adquisición de 614 ATMs (ETMs ). Queda pendiente la gestión del proceso logístico para la instalación (está en evaluación del usuario). El control de cambios se debe realizar por el tiempo, alcance y presupuesto segun corresponda. Pendiente que el usuario remita modelo de negocio para registrar el Proyecto en la demanda estrategica priorizada.
A19: 17 | B19: PROAMP-EO08-23-9 | C19: Actualización del Manual de procesos del BN y Elaboración de documentos normativos enfocado a procesos | D19: El proyecto se ha constituido con la finalidad identificar y estructurar los diferentes procesos y procedimientos (actividades) que constituyen la totalidad de los Macroprocesos, la formalización se realizará mediante Directivas y Manuales de Procedimientos que norman las responsabilidades, lineamientos y reglas de negocio det proceso, así como la secuencia de tareas, responsables, herramientas,entreotros,formatos,respectivamente | E19: Planeamiento y Control de Gestión | F19: Iris Javier | G19: Miguel Casma | H19: Maria Isabel Elguera | I19: 0 | M19: 45121 | N19: Acta Nº8-2023 | Q19: 2023 | R19: 2025 | S19: 2 | T19: No | U19: No | V19: Manual de procesos | W19: No | X19: No definido | Y19: 44991 | Z19: 46022 | AA19: 0.71 | AB19: 0.6 | AC19: =Tabla3[[#This Row],[% Avance ejecutado]]-Tabla3[[#This Row],[% Avance Planificado]]/Tabla3[[#This Row],[% Avance Planificado]] -> -0.4 | AD19: 04. Cerrado | AE19: CERRADO 21/08/2025: De acuerdo al Acta de Comité de Proyectos del 14/08 N°07-2025 se informa que: Se aprueba el cierre del proyecto. 18/08/25: Según la información enviada de Planeamiento en el mes de Julio se precisa lo siguiente: Esta presentado su informe y acta de cierre para ser elevado al Comité ejecutivo de proyectos. 18/07/2025: EN PROCESO DE CIERRE- Para el siguiente comité van a presentar su solicitud de cierre ante el comité ejecutivo de proyectos 11/06/2025:Según la información enviada de Planeamiento en el mes de Mayo se precisa lo siguiente: Se tienen demoras debido a la falta de un analista de procesos dedicado a la ejecución de directivas y manuales de procedimiento de los macroprocesos. Adicionalmente, la reasignación de miembros del equipo a otras funciones o proyectos ha impactado negativamente. A esto se suma la demora en la revisión y aprobación de las directivas y manuales de procedimiento por parte de las unidades orgánicas rectoras 03/06/2025: Según la información enviada de Planeamiento mediante correo respecto al proyecto en el mes de abril se tiene que: Dos de cinco entregables están listos, pero el avance de los entregables 3 y 4 se ha retrasado. Su finalización depende de la aprobación oficial de las Directivas y Manuales de Procedimientos por las áreas correspondientes.
A20: 18 | B20: PRODEO-EO08-23-10 | C20: Análisis y validación del Mapa de Procesos, Diagnóstico de Estructura Organizacional y Estudio de Carga Laboral del BN | D20: El proyecto se ha constituido con el fin de lograr un modelo organizacional con un enfoque de procesos; el cual se desarrollará en dos etapas secuenciales, la primera consta del análisis y validación del Mapa de Procesos, Diagnóstico de Estructura Organizacional y Estudio de Carga Laboral del Banco a cargo de una empresa especializada y la segunda estará a cargo de la Subgerencia Desarrollo Organizacional quien evaluará las recomendaciones, elaborará la propuesta final y gestionará la aprobación de los documentos de gestión como son el Reglamento de Organización de Funciones (ROF), el Cuadro de Asignación de Personal (CAP) y el Manual de Organización de Funciones MOF . | E20: Planeamiento y Control de Gestión | F20: Luis Avilez | G20: - | H20: No definido | I20: 493750 | J20: =Tabla3[[#This Row],[Presupuesto asignado]]/2 -> 246875 | K20: =Tabla3[[#This Row],[Valor Ganado (EV)]] -> 246875 | L20: =Tabla3[[#This Row],[Valor Ganado (EV)]]/Tabla3[[#This Row],[Costo Actual (AC)]] -> 1 | M20: 45121 | N20: Acta Nº8-2023 | O20: Estrategia y Gobernanza | P20: Gestión Interna | Q20: 2023 | R20: 2025 | T20: No | U20: Si | V20: Manual de procesos y documentos normativos enfocados a procesos | W20: No Aplica | X20: No Aplica | Y20: 45061 | Z20: 45707 | AA20: 1 | AB20: 1 | AC20: =Tabla3[[#This Row],[% Avance ejecutado]]-Tabla3[[#This Row],[% Avance Planificado]]/Tabla3[[#This Row],[% Avance Planificado]] -> 0 | AD20: 03. Implementado | AE20: IMPLEMENTADO 11/06/2025:Según la información enviada de Planeamiento en el mes de Mayo se precisa lo siguiente: Se considera las tareas cerradas. 03/06/2025: Según la información enviada de Planeamiento mediante correo respecto al proyecto en el mes de abril se tiene que: Los ocho entregables clave del proyecto, incluyendo el MOF, ROF y CAP, ya están aprobados. Aunque falta documentación formal y de cierre, el proyecto se considera sustancialmente terminado. 21/05/2025: Según el Acta de Reunión N°04-2025 del Comité de Proyectos, se aprobó el Control de Cambios con fecha final a diciembre del 2025. 07/05/2025: Según la información remitida por Planeamiento mediante correo: Se han completado 7 de los 9 entregables. El 8vo está pendiente de cierre, a la espera de la aprobación del directorio del Documento de Gestión CAP. 31/12/2024: Solo faltaría la aprobación del CAP y finaliza con actividades del cierre del proyecto. 23/05/24 Se esta trabajando con Proveedor Xperta. Presentarán un control de cambio. 09/04/24 Se introdujo información del dashboard consolidado de proyectos al 31.02.24 que se menciona que el proyecto tiene un avance del 35% valor que se repite desde Diciembre 2023.
A21: 19 | B21: ID N° | C21: Centro de Operaciones de Ciberseguridad | E21: Tecnologías de Información | F21: - | G21: - | H21: No definido | I21: 28478866 | J21: =Tabla3[[#This Row],[Presupuesto asignado]]/2 -> 14239433 | K21: =Tabla3[[#This Row],[Valor Ganado (EV)]] -> 14239433 | L21: =Tabla3[[#This Row],[Valor Ganado (EV)]]/Tabla3[[#This Row],[Costo Actual (AC)]] -> 1 | M21: 45271 | N21: Acta N°10-2023 | O21: Tecnológica | T21: Si | U21: No | V21: Operaciones de Ciberseguridad | W21: No | X21: No Aplica | AA21: 0 | AB21: 0 | AC21: =Tabla3[[#This Row],[% Avance ejecutado]]-Tabla3[[#This Row],[% Avance Planificado]]/Tabla3[[#This Row],[% Avance Planificado]] -> #DIV/0! | AD21: 03. Implementado | AE21: Mediante acta de 10-2023 del 11/12 se aprobó la división en 4 Proyectos.
A22: 20 | B22: ID N° | C22: Centro de Operaciones de Ciberseguridad 1 – Servicio Solución de Seguridad contra Boots | D22: Servicio Solución de Seguridad contra Bots | E22: Tecnologías de Información | F22: Ana Li | G22: Ricardo Siancas | H22: No definido | I22: 2007994.2 | J22: =Tabla3[[#This Row],[Presupuesto asignado]]/2 -> 1003997.1 | K22: =Tabla3[[#This Row],[Valor Ganado (EV)]] -> 1003997.1 | L22: =Tabla3[[#This Row],[Valor Ganado (EV)]]/Tabla3[[#This Row],[Costo Actual (AC)]] -> 1 | M22: 45271 | N22: Acta N°10-2023 | O22: Tecnológica | P22: De cara al ciudadano | Q22: 2023 | R22: 2024 | T22: Si | U22: Si | V22: COC01 | W22: No | X22: Ana María Li | Y22: 45271 | Z22: 45412 | AA22: 1 | AB22: 1 | AC22: =Tabla3[[#This Row],[% Avance ejecutado]]-Tabla3[[#This Row],[% Avance Planificado]]/Tabla3[[#This Row],[% Avance Planificado]] -> 0 | AD22: 03. Implementado | AE22: IMPLEMENTADO 23/05/24 De acuerdo al correo del MIsabel del 23/05 el proyecto esta implementado. TI remitió acta de cierre y lecciones aprendidas. 25/04/2024 Mediante Memo N° 63-2024-BN2810 en que se entrega la nueva lista de proyectos con componente TI en el mismo se registra nuevo Lider del proyecto por lo que se procede al cambio correspondiente de Ricardo Siancas a Ana Li. Se constata que el proyecto fue aprobado el 11.12.23 según acta de comité. 21/03/24 Culminaron los TDR, se encuentran en estudion de mercado y finalizando los formatos de riesgos. Registrado en la demanda estratégica priorizada
A23: 21 | B23: ID N° | C23: Centro de Operaciones de Ciberseguridad 2 - Protección avanzada en endpoints y la red del BN | D23: Servicio de Solución para la Protección avanzada en End-points y la red del BN | E23: Tecnologías de Información | F23: Ana Li | G23: Ricardo Siancas | H23: No definido | I23: 10992000 | J23: =Tabla3[[#This Row],[Presupuesto asignado]]/2 -> 5496000 | K23: =Tabla3[[#This Row],[Valor Ganado (EV)]] -> 5496000 | L23: =Tabla3[[#This Row],[Valor Ganado (EV)]]/Tabla3[[#This Row],[Costo Actual (AC)]] -> 1 | M23: 45271 | N23: Acta N°10-2023 | O23: Tecnológica | P23: De cara al ciudadano | Q23: 2023 | R23: 2024 | T23: Si | U23: Si | V23: COC02 | W23: No | X23: Ana María Li | Y23: 45271 | Z23: 45471 | AA23: 1 | AB23: 1 | AC23: =Tabla3[[#This Row],[% Avance ejecutado]]-Tabla3[[#This Row],[% Avance Planificado]]/Tabla3[[#This Row],[% Avance Planificado]] -> 0 | AD23: 03. Implementado | AE23: IMPLEMENTADO 23/05/24 En Marzo24 se dio inicio a la ejecución. 25/04/2024 Mediante Memo N° 63-2024-BN2810 en que se entrega la nueva lista de proyectos con componente TI en el mismo se registra nuevo Lider del proyecto por lo que se procede al cambio correspondiente de Ricardo Siancas a Ana Li. Se constata que el proyecto fue aprobado el 11.12.23 según acta de comité. 25/04/2024 Mediante Memo N°60-2024-BN2810 se informa que se requiere el informe de las razones del retraso del proyecto asi como sus acciones correctivas para la presentación al comité del 26.04 21/03/24 Se firmó el contrato el 08/02/24 y se dio inicio a la implementación. Registrado en la demanda estratégica priorizada
A24: 22 | B24: ID N° | C24: Centro de Operaciones de Ciberseguridad 3 - Gestión de Vulnerabilidades | D24: Gestión de vulnerabilidades y Políticas de FW | E24: Tecnologías de Información | F24: Ana Li | G24: Ricardo Siancas | H24: No definido | I24: 41200 | J24: =Tabla3[[#This Row],[Presupuesto asignado]]/2 -> 20600 | K24: =Tabla3[[#This Row],[Valor Ganado (EV)]] -> 20600 | L24: =Tabla3[[#This Row],[Valor Ganado (EV)]]/Tabla3[[#This Row],[Costo Actual (AC)]] -> 1 | M24: 45271 | N24: Acta N°10-2023 | O24: Tecnológica | P24: De cara al ciudadano | Q24: 2023 | R24: 2024 | T24: Si | U24: Si | V24: COC03 | W24: No | X24: Ana María Li | Y24: 45271 | Z24: 45645 | AA24: 1 | AB24: 1 | AC24: =Tabla3[[#This Row],[% Avance ejecutado]]-Tabla3[[#This Row],[% Avance Planificado]]/Tabla3[[#This Row],[% Avance Planificado]] -> 0 | AD24: 03. Implementado | AE24: IMPLEMENTADO 31/12/2024: Se culminó con todas las tareas planificadas para el proyecto: *Suscripción herramienta de Análisis de Vulnerabilidades: 100% *Implementación herramienta de Vulnerabilidades – Wazuh: 100% *Servicio de Soporte Especializadas en Inteligencia de Ciberseguridad: 100% *Servicio Escaneo Externo Asv Pci: 100% *Servicio de Prueba de Penetración a Base De Datos: 100% 23/05/24 Cuenta con 5 fases, pendiente soporte especializado, escaneo externo, prueba de penetración a BD (con retraso). 25/04/2024 Mediante Memo N° 63-2024-BN2810 en que se entrega la nueva lista de proyectos con componente TI en el mismo se registra nuevo Lider del proyecto por lo que se procede al cambio correspondiente de Ricardo Siancas a Ana Li. Se constata que el proyecto fue aprobado el 11.12.23 según acta de comité. 21/03/24 Seguridad Informática se encuentra actualizando los TDRs. Registrado en la demanda estratégica priorizada
A25: 23 | B25: ID N° | C25: Centro de Operaciones de Ciberseguridad 4 - Gestión de Correlación de Eventos | D25: Gestión de correlación de eventos | E25: Tecnologías de Información | F25: Ana Li | G25: Ricardo Siancas | H25: No definido | I25: 40900 | J25: =Tabla3[[#This Row],[Presupuesto asignado]]/2 -> 20450 | K25: =Tabla3[[#This Row],[Valor Ganado (EV)]] -> 20450 | L25: =Tabla3[[#This Row],[Valor Ganado (EV)]]/Tabla3[[#This Row],[Costo Actual (AC)]] -> 1 | M25: 45271 | N25: Acta N°10-2023 | O25: Tecnológica | P25: De cara al ciudadano | Q25: 2023 | R25: 2024 | T25: Si | U25: Si | V25: COC04 | W25: No | X25: Ana María Li | Y25: 45271 | Z25: 45376 | AA25: 1 | AB25: 1 | AC25: =Tabla3[[#This Row],[% Avance ejecutado]]-Tabla3[[#This Row],[% Avance Planificado]]/Tabla3[[#This Row],[% Avance Planificado]] -> 0 | AD25: 03. Implementado | AE25: IMPLEMENTADO 02/04/2024: Se comunico en el ultimo Comité de Proyectos, estado implementado 21/03/24 Esta paralizado, por que están evaluando por dos meses el comportamiento de la herramienta el Wazuh "reporte de alerta y amenazas". Si está herramienta funciona bien, se descartará el proyecto en coordinación con P&D. Registrado en la demanda estratégica priorizada
A26: 24 | B26: ID N° | C26: Digitalización de documentos, uso de firma electrónica avanzada y titulo valor electrónico, en el otorgamiento de créditos minoristas en canales minoristas en canales no presenciales | E26: Productos e Inclusión Financiera | G26: - | I26: 0 | J26: =Tabla3[[#This Row],[Presupuesto asignado]]/2 -> 0 | K26: =Tabla3[[#This Row],[Valor Ganado (EV)]] -> 0 | L26: =Tabla3[[#This Row],[Valor Ganado (EV)]]/Tabla3[[#This Row],[Costo Actual (AC)]] -> #DIV/0! | O26: Servicio a los Clientes | P26: De cara al ciudadano | T26: No | U26: No | V26: Digitalización de documentos y uso de firma electrónico avanzada | W26: No Aplica | X26: No Aplica | AA26: 0 | AB26: 0 | AC26: =Tabla3[[#This Row],[% Avance ejecutado]]-Tabla3[[#This Row],[% Avance Planificado]]/Tabla3[[#This Row],[% Avance Planificado]] -> #DIV/0! | AD26: 05. Descartado | AE26: Mediante acta de 10-2023 del 11/12 se cerró para considerar como Proyecto de mejora.
A27: 25 | B27: ID N° | C27: Rediseño y desarrollo de Banca Personal en canales no presenciales (App, Web y Empresas externas de ventas). | E27: Productos e Inclusión Financiera | G27: - | I27: 0 | J27: =Tabla3[[#This Row],[Presupuesto asignado]]/2 -> 0 | K27: =Tabla3[[#This Row],[Valor Ganado (EV)]] -> 0 | L27: =Tabla3[[#This Row],[Valor Ganado (EV)]]/Tabla3[[#This Row],[Costo Actual (AC)]] -> #DIV/0! | O27: Servicio a los Clientes | P27: De cara al ciudadano | T27: No | U27: No | V27: Rediseño de Banca Personal en canales no presenciales | W27: No Aplica | X27: No Aplica | AA27: 0 | AB27: 0 | AC27: =Tabla3[[#This Row],[% Avance ejecutado]]-Tabla3[[#This Row],[% Avance Planificado]]/Tabla3[[#This Row],[% Avance Planificado]] -> #DIV/0! | AD27: 05. Descartado | AE27: Mediante acta de 10-2023 del 11/12 se cerró para considerar como Proyecto de mejora.
A28: 26 | B28: ID N° | C28: Mejora y ampliación de canales externos para el otorgamiento de préstamos Multired-IVR | E28: Productos e Inclusión Financiera | F28: Piero Flores | G28: - | H28: No definido | I28: 0 | J28: =Tabla3[[#This Row],[Presupuesto asignado]]/2 -> 0 | K28: =Tabla3[[#This Row],[Valor Ganado (EV)]] -> 0 | L28: =Tabla3[[#This Row],[Valor Ganado (EV)]]/Tabla3[[#This Row],[Costo Actual (AC)]] -> #DIV/0! | M28: 45271 | N28: Acta N°10-2023 | O28: Servicio a los Clientes | P28: De cara al ciudadano | Q28: 2024 | R28: 2024 | T28: Si | U28: No | V28: Préstamos Multired | W28: Sí | X28: Pedro Encalada | Y28: 45294 | Z28: 45538 | AA28: 1 | AB28: 1 | AC28: =Tabla3[[#This Row],[% Avance ejecutado]]-Tabla3[[#This Row],[% Avance Planificado]]/Tabla3[[#This Row],[% Avance Planificado]] -> 0 | AD28: 03. Implementado | AE28: IMPLEMENTADO 23/05/2024 Mediante acta del Comité Estratégico de proyectos de fecha 06.05.24 se informa la aprobación del control de cambios del proyecto, los usuarios deben formalizar el nuevo cronograma del proyecto y remitirlo a planeamiento. Validar que prestamo por Call Center esté en marcha blanca. 03/05/2024 Se atendió la implementación de préstamos Multired por IVR 26/04/2024 Con correo emitido por Yamela Valenzuela se entrega la propuesta del cronograma del proyecto esperando la respuesta. 21/3/2024 Se agendará una reunión para revisar las siguientes actividades que involucran a TI. Pendiente que el usuario remita modelo de negocio para registrar el Proyecto en la demanda estrategica priorizada.
A29: 27 | B29: ID N° | C29: Diagnostico de Madurez de Gestion de Proyectos y Plan de Trabajo de Implementacion de PMO | D29: Establecer una estructura y procesos para promover una cultura de proyectos y elevar el nivel de madurez del Banco en la gestión de proyectos. Se desarrollarán mecanismos de seguimiento, control y comunicación con los interesados, se mejorarán las metodologías y herramientas de gestión de proyectos, y se gestionarán las metodologías, estándares, riesgos, oportunidades, métricas e interdependencias entre proyectos. Además, se brindará capacitación a los equipos de gestión de cartera y proyectos para fortalecer sus habilidades y conocimientos. | E29: Planeamiento y Control de Gestión | G29: - | I29: 100000 | J29: =Tabla3[[#This Row],[Presupuesto asignado]]/2 -> 50000 | K29: =Tabla3[[#This Row],[Valor Ganado (EV)]] -> 50000 | L29: =Tabla3[[#This Row],[Valor Ganado (EV)]]/Tabla3[[#This Row],[Costo Actual (AC)]] -> 1 | O29: Personas y Cultura Organizacional | P29: Gestión Interna | Q29: 2023 | R29: 2023 | T29: No | U29: Si | V29: Proyectos y PMO | W29: No Aplica | X29: No Aplica | Y29: 44958 | Z29: 45261 | AA29: 1 | AB29: 1 | AC29: =Tabla3[[#This Row],[% Avance ejecutado]]-Tabla3[[#This Row],[% Avance Planificado]]/Tabla3[[#This Row],[% Avance Planificado]] -> 0 | AD29: 03. Implementado | AE29: IMPLEMENTADO 31/12/2024: Falta de personal en el equipo. Asimismo, las tareas pendientes requieren coordinaciones entre las áreas responsables, lo cual está tomando más tiempo del previsto. 09/04/24 Se introdujo información del dashboard consolidado de proyectos al 31.02.24 que se menciona que el proyecto a culmiado a Diciembre del 2023
A30: 28 | B30: ID N° | C30: Plan de Transfomación Cultural BN | D30: Crear las condiciones necesarias para fomentar un cambio de mentalidad y comportamiento en todos los niveles de la organización, promoviendo una cultura de colaboración, flexibilidad, adaptabilidad y aprendizaje constante. Se implementarán iniciativas como programas de capacitación, comunicación interna, establecimiento de espacios de trabajo colaborativos y promoción de la participación activa de los empleados en la identificación y ejecución de mejoras. | E30: Recursos Humanos y Cultura | G30: - | I30: 985176 | J30: =Tabla3[[#This Row],[Presupuesto asignado]]/2 -> 492588 | K30: =Tabla3[[#This Row],[Valor Ganado (EV)]] -> 492588 | L30: =Tabla3[[#This Row],[Valor Ganado (EV)]]/Tabla3[[#This Row],[Costo Actual (AC)]] -> 1 | O30: Personas y Cultura Organizacional | P30: Gestión Interna | Q30: 2023 | R30: 2025 | T30: No | U30: No | V30: Cultura BN | W30: No Aplica | X30: No Aplica | Y30: 44928 | Z30: 45666 | AA30: 1 | AB30: 1 | AC30: =Tabla3[[#This Row],[% Avance ejecutado]]-Tabla3[[#This Row],[% Avance Planificado]]/Tabla3[[#This Row],[% Avance Planificado]] -> 0 | AD30: 04. Cerrado | AE30: 08/04/2025: Mediante el Acta de Reuniòn 01-2025 del Comitè de Proyectos se aprobò la exclusiòn del proyecto del Portafolio de Proyectos debido a que las actividades contempladas a cargo de la secciòn de Cultura Organizacional estan contempladas dentro del marco de sus funciones asignadas y son actividades recurrentes. 23/05/24 En ejecución 09/04/24 Según informe consolidado del dashboard de oproyectos al 31.02.24 se registra la operación con un avance del 25% cumpliendo lo planificado
A31: 29 | B31: ID N° | C31: Implementación de un gestor integración por API'S. | D31: Implementación de una arquitectura tecnológica basada en Interface de Programación de Aplicaciones (API’s), incluyendo el despliegue de un API Gateway y Management, considerando la reutilización de lógica de negocio existente en los sistemas Legacy en combinación con nuevos desarrollos en plataformas tecnológicamente modernas en el Banco de la Nación. | E31: Tecnologías de Información | F31: Fernando Avellaneda | G31: - | I31: 119232324 | J31: =Tabla3[[#This Row],[Presupuesto asignado]]/2 -> 59616162 | K31: =Tabla3[[#This Row],[Valor Ganado (EV)]] -> 59616162 | L31: =Tabla3[[#This Row],[Valor Ganado (EV)]]/Tabla3[[#This Row],[Costo Actual (AC)]] -> 1 | O31: Tecnológica | P31: De cara al ciudadano | Q31: 2023 | R31: 2023 | T31: Si | U31: Si | V31: Gestor por API'S | W31: No | X31: Fernando Avellaneda | Y31: 44958 | Z31: 45230 | AA31: 1 | AB31: 1 | AC31: =Tabla3[[#This Row],[% Avance ejecutado]]-Tabla3[[#This Row],[% Avance Planificado]]/Tabla3[[#This Row],[% Avance Planificado]] -> 0 | AD31: 03. Implementado | AE31: IMPLEMENTADO 09/04/24 Según el Dashboard de proyectos a 31.02.24 el proyecto se encuentra como culminado a Octubre del 2023, valor que se repite desde Diciembre 2023. Se ingresa la información correspondiente.
A32: 30 | B32: PROIGD-EO08-23-32 | C32: Implementación de Gobierno de Datos | D32: Debido a que el BN no cuenta con un programa de gobierno de datos que integre políticas, procesos, prácticas y tecnologías diseñadas para asegurar la calidad, integridad, disponibilidad y seguridad de los datos es que se crea el proyecto, para garantizar el acceso y uso adecuado de los datos | E32: GIT | F32: Juan Berrospi | G32: - | H32: Rina Roca | I32: Recursos Propios | M32: 45271 | N32: Acta N°10-2023 | O32: Estrategia y Gobernanza | P32: Gestión Interna | Q32: 2023 | R32: 2026 | S32: 0 | T32: No | U32: Si | V32: Gobierno Datos | W32: No Aplica | X32: No Aplica | Y32: 45173 | Z32: 46387 | AA32: 0.87 | AB32: 0.93 | AC32: =Tabla3[[#This Row],[% Avance ejecutado]]-Tabla3[[#This Row],[% Avance Planificado]]/Tabla3[[#This Row],[% Avance Planificado]] -> -0.07 | AD32: 04. Cerrado | AE32: 23/03/2026: Para el cierre de febrero, se formaliza el cierre del proyecto según acuerdos de comité (23.01.26 y 03.03.2026), retirándolo del portafolio y gestionando el acta de cierre y lecciones aprendidas. Al cierre de febrero se alcanzó un 93% de avance, completando el marco normativo y de gobierno de datos, quedando pendientes el plan de comunicación/capacitación y el de metadatos y taxonomías. 20/03/2026: Según el acta de reunión del comité de proyectos del mes de enero, el proyecto marchó de acuerdo a lo planificado al cierre de diciembre 2025. El marco normativo de gobierno de datos fue implementado, incluyendo Política, Directiva, MAPRO, Estrategia y calidad de datos. El proyecto será retirado del Portafolio de proyectos, dado que las actividades que viene realizando son parte de sus funciones y requieren un alcance más amplio y consistente con las obligaciones normativas y operativas del BN. 25/02/2026: El documento de Dominio de datos fue aprobado por la Gerencia de Innovacion y Transformacion Digital el pasado 21,01,2026. El caso de la inclusión de los datos a las Mapros que comprenden el dominio cliente, se retomo con la asignación de un nuevo analista de la subgerencia de Desarrollo. 21/01/2026: El marco normativo de Gobierno de Datos ya fue implementado e incluye Política, Directiva, MAPRO de Gobierno de Datos, Estrategia y Calidad de Datos. En materia de Calidad de Datos, se implementó la directiva BN-PRO-7800-178-01 – Manual de Procedimientos para medir la calidad de los datos. Respecto al plan, se viene desarrollando el proceso de gobierno del dominio Clientes, incorporando los datos en los Manuales de Procesos. Actualmente, la Subgerencia de Desarrollo mapea los datos del proceso de apertura de cuentas, como parte de los 8 dominios del Banco. Culminado el mapeo y la aprobación de los dominios, la Gerencia de Planeamiento iniciará la comunicación de roles y responsabilidades en el marco de Gobierno de Datos. 30/09/2025: Según la información enviada de Planeamiento en el mes de Septiembre se precisa lo siguiente: Al cierre del mes de setiembre, se va ejecutándose según lo planificado. Se encuentra en espera la programación para la reunión del Comité de Gobierno y Transformación, estimado para el mes de octubre, para la aprobación del Informe de Dominios de Datos. Una vez aprobado el informe, se procederá a comunicar a los propietarios de los datos los roles, funciones y responsabilidades a los propietarios de los datos. 16/09/2025:Según la información enviada de Planeamiento en el mes de Agosto se precisa lo siguiente: Al cierre del mes de agosto, viene ejecutándose en un porcentaje mayor a lo planificado. Asimismo, el informe del dominio de datos fue elevada al comité de Gobierno y Transformación Digital, para su sesión fue reprogramada para el 02.09.25; en ese sentido, luego de su socialización se ha remitido un correo solicitando la colaboración de las áreas involucradas para obtener el visto bueno correspondiente y, de esta manera, poder elevarlo al Comité en la nueva fecha. Una vez aprobado, se procederá a comunicar los roles, funciones y responsabilidades de calidad de datos a los propietarios de los datos. 18/08/25: Según la información enviada de Planeamiento en el mes de Julio se precisa lo siguiente: El proyecto viene ejecutándose de acuerdo a lo planificado, a nivel de tareas con un avance mayor a lo esperado. Asimismo, con respecto al plan de comunicación y capacitación, se cuenta con el informe de Dominios de datos del banco, el cual ha sido elevado al comité de gobierno y transformación digital para su aprobación en su próxima sesión (se estima en agosto próximo). 18/07/2025: A nivel tareas al 30.06.25, se viene revisando el documento de roles y responsabilidades de los Dueños de Datos del dominio Cliente, con miras a su envío a la Gerencia de Planeamiento para su posterior comunicación con los lideres de datos (dueños de los procesos). 11/06/2025:Según la información enviada de Planeamiento en el mes de Mayo se precisa lo siguiente: En relación con el documento de asignación de roles dentro de la estructura de Gobierno de Datos, se han recibido las opiniones técnicas por parte de las áreas de Recursos Humanos y Asesoría Legal. En ese marco, se procederá a remitir el documento a la Gerencia de Planeamiento, a fin de que esta, en su calidad de unidad funcionalmente competente, lo canalice hacia los Líderes de Datos del Dominio Clientes. Se ha elaborado el Informe de Dominios de Datos del Banco de la Nación, el cual se tiene previsto presentar al Comité de Gobierno y Transformación Digital para su revisión y aprobación formal. 03/06/2025: Según la información enviada de Planeamiento mediante correo respecto al proyecto en el mes de abril se tiene que: Con respecto al fortalecimiento del área, oficina o función de Gobierno de Datos se incorporó personal practicante, asu vez, el concurso externo que se encuentra en curso proyectando incorporar (01) especialista en machine learning y (01) analista de calidad de datos. Se ha elaborado el documento de asignación de roles y responsabilidades referidos al dominio cliente remitido a las áreas involucradas (Legal y Recursos Humanos) para su revisión y opinión formal. 07/05/2025: Según la información remitida por Planeamiento mediante correo: Se aprobó la directiva de Gobierno de Datos del BN, asimismo se viene entrevistando al personal para la subgerencia de datos y analítica avanzada con fines de fortalecimiento del área, Se ha elaborado el documento de asignación de roles y responsabilidades referidos al domino cliente remitiendo a las áreas involucradas (Gerencia de Operaciones, Subgerencia de Pagaduría, OPLAFT, TI, BPIF, Red de Agencias, Riesgos) para su opinión. 31/12/2024: Entre las actividades se encuentra en curso el proceso de publicación de la directiva de gobierno de datos la misma que permitirá formalizar la comunicación de los roles, funciones y responsabilidades de calidad de datos, asimismo permitirá iniciar las reuniones con la gerencia de planeamiento para definir e inventariar los metadatos y taxonomía. 23/05/24 Se encuentran elaborando las directivas asociadas, no tienen componente tecnológico. 13/05/2024 A la espera del Anexo 1 para la incorporación del proyecto a la demanda estratégica 03/05/2024 En revisión de la estrategia de Gobierno de Datos 25/04/2024 Mediante Memo N° 63-2024-BN2810 en que se entrega la nueva lista de proyectos con componente TI en el mismo se registra nuevo Lider del proyecto por lo que se procede al cambio correspondiente de Luis Lavado a Juan Berrospi. 21/3/2024 Proyecto Nuevo. Según cronograma, TI participará en la actividad de implementación del la aquitectura de Datos (se estima set24) 11/12/2023: Mediante Acta de Comité Ejecutivo de Proyectos N°010-2023 se aprobó el proyecto
A33: 31 | B33: PROTAIT-EO10-24-36 | C33: Traslado y Alojamiento de Infraestructura Tecnológica del actual Centro de datos de respaldo BN - San Isidro | D33: Traslado (Moving) de la infraestructura tecnológica del actual Centro de Datos de Respaldo BN (San isidro) — ubicado en el 3er Piso de la Sede del Tribunal Constitucional San Isidro — a una nueva ubicación, fuera de las instalaciones del BN, para el atojamiento (Housing) de la infraestructura tecnológica, en ambientes de un proveedor de servicios que cuente mínimamente con Certificación TIER III o Rated 3 0 ICREA Nivel IV y que este ubicado en un edificio inteligente moderno con altas capacidades de resiliencia y arquitectura antisismicas | E33: Tecnologías de Información | F33: Alejandro Sifuentes | G33: - | H33: Maria Isabel Elguera | I33: 0 | M33: 45376 | N33: Acta Nº2-2024 | O33: Tecnológica | P33: Gestión Interna | Q33: 2024 | R33: 2025 | T33: Si | U33: Sí | V33: Traslado Centro Datos | W33: Si | X33: Jesus Chavarría | Y33: 45338 | Z33: 45846 | AA33: 0.9 | AB33: 0.26 | AC33: =Tabla3[[#This Row],[% Avance ejecutado]]-Tabla3[[#This Row],[% Avance Planificado]]/Tabla3[[#This Row],[% Avance Planificado]] -> -0.74 | AD33: 04. Cerrado | AE33: CERRADO 26/08/2025: De acuerdo al Acta de Comité de Proyectos del 16/07 N°06-2025 se informa que: Se aprobó el cierre formal del proyecto. 18/07/2025: Considerando que se ha logrado el objetivo estratégico del proyecto mediante la permanencia asegurada del Centro de Datos de Respaldo en su ubicación actual, se considera oportuno cerrar el proyecto ya que la necesidad de trasladar el centro de datos ya no esta latente y tenemos una ampliación de plazo debido a una negociación con el TC. Ante ello, la gerencia de TI solicitó el cierre del proyecto dentro del portafolio de proyectos. 11/06/2025:Según la información enviada de Planeamiento en el mes de Mayo se precisa lo siguiente: El Equipo Técnico continuará con el seguimiento de las actividades relacionadas con la condición suspensiva, asegurando su cumplimiento dentro del plazo estipulado. Con la aceptación de la minuta y la culminación de las actividades suspensivas, el proyecto alcanza su fase de cierre. Se procederá con el envío del informe y el formato de cierre de proyecto, incluyendo las lecciones aprendidas. 03/06/2025: Según la información enviada de Planeamiento mediante correo respecto al proyecto en el mes de abril se tiene que: A nivel tareas, el Equipo Técnico informó que las actividades del proyecto continúan en estado de espera debido a la negociación en curso de la extensión del plazo de cesión en uso de los ambientes ocupados por el Data Center de Contingencia del Banco hasta octubre del 2028 con el Tribunal Constitucional, cuyo resultado determinará la continuidad o cierre del proyecto. Si la negociación no prospera, las actividades pendientes se reanudarán conforme al plan establecido. Actualmente, en espera de la respuesta formal del Tribunal Constitucional al proyecto enviado el 7/03/2025 por la Gerencia General, donde se propone una ampliación de plazo por la cesión de uso de espacio físico donde se aloja el Data Center hasta por tres (03) años (10/2029). 21/05/2025: Según el Acta de Reunión N°04-2025 del Comité de Proyectos, la Gerencia líder debe esperar la respuesta del Tribunal Constitucional para elaborar el Acta de Cierre del Proyecto y el formato de captura de lecciones aprendidas. 07/05/2025: Según la información remitida por Planeamiento mediante correo: A nivel tareas, el Equipo Técnico informó que las actividades del proyecto continúan en estado de espera debido a la negociación en curso de la extensión del plazo de cesión en uso de los ambientes ocupados por el Data Center de Contingencia del Banco hasta octubre del 2028 con el Tribunal Constitucional, cuyo resultado determinará la continuidad o cierre del proyecto. Si la negociación no prospera, las actividades pendientes se reanudarán conforme al plan establecido. Actualmente, en espera de la respuesta formal del Tribunal Constitucional al proyecto enviado el 7/03/2025 por la Gerencia General, donde se propone una ampliación de plazo por la cesión de uso de espacio físico donde se aloja el Data Center hasta por tres (03) años (06 oct 2029). 31/12/2024: El proyecto se encuentra a la espera de la respuesta del Tribunal Constitucional para que indiquen si el tiempo de permanencia del centro de datos se aplaza o no. 23/05/24 TI concluyo con la alaboración del TDR, pendiente envío a Logistica para inicio de estudio de MErcado. 03/05/2024 En elaboración de TDR's y otros documentos para iniciar el estudio del mercado. 25/04/2024 Mediante Memo N° 63-2024-BN2810 en que se entrega la nueva lista de proyectos con componente TI en el mismo se registra nuevo Lider del proyecto por lo que se procede al cambio correspondiente de José Macedo a Alejandro Sifuentes. 10/04/2024 Con correo se envía el memorando N°00000044-2024-BN/2810 "Retraso de envío de información" comunica que el pedido fue atendido mediante memorando 00000012-2024-BN/2540 a la fecha de 08.04.2024. Proyecto fue aprobado por el Comité ejecutivo de Proyectos el 27.03.2024 solicitando ajustes a los documentos iniciales que fueron atendidos y enviados por medio de correo.
A34: 32 | B34: PROTTES-EO04-24-34 | C34: Tarjeta Tesoro | D34: Implementar el producto "Tarjeta Tesoro" en el Banco de la Nación, bajo la marca Mastercard, dirigido a satisfacer la necesidad de las Entidades Públicas de contar con un medio de pago, eficiente en la administración y control, fácil y seguro de usar expeditivo en la distribución y de óptimo costo de operación, con la finalidad de reemplazar el uso del dinero en efectivo en la asignación de viáticos por comisión de servicio, comisiones por encargo y de caja chica, que actualmente se le otorga a lo colaboradores públicos cuando así se requiere. Adicionalmente, la Tarjeta de Tesoro también permite satisfacer los requerimientos para compras menores, compras por intemet y abastecimiento de combustible. | E34: Productos e Inclusión Financiera | F34: Cecilia Arias | G34: Peter Valencia | H34: Juan Carlos Palomino | I34: 0 | M34: 45376 | N34: Acta Nº2-2024 | O34: Por asignar | P34: Por asignar | Q34: 2024 | R34: 2025 | S34: 2 | T34: Si | U34: Sí | V34: Tarjeta Tesoro | W34: Si | X34: Por asignar | Y34: 45306 | Z34: 46018 | AA34: 0.86 | AB34: 0.84 | AC34: =Tabla3[[#This Row],[% Avance ejecutado]]-Tabla3[[#This Row],[% Avance Planificado]]/Tabla3[[#This Row],[% Avance Planificado]] -> -0.16 | AD34: 04. Cerrado | AE34: 23/03/2026: En el cierre de febrero, la falta de respuesta del MEF sobre el diseño de tarjetas y la normativa ha condicionado el avance, impidiendo cumplir lo planificado; por ello, en el Comité del 03/03/2026 se acordó retirarlo de la cartera de proyectos estratégicos. 20/03/2026: Según el acta de reunión del comité de proyectos del mes de enero, el proyecto presentó retraso al cierre de diciembre 2025. Se confirmó la participación del Ministerio de Relaciones Exteriores, MEF y Tesoro Público, iniciándose las pruebas en enero 2026. La Directiva "Tarjeta de crédito corporativa" se encuentra en validación, con opinión pendiente de Fraude y Riesgo. Existe dependencia del MEF para el diseño de las tarjetas, con respuesta esperada a mediados de febrero 2026. La Gerencia de Planeamiento y Control de Gestión debe solicitar a la gerencia responsable y a TI la cuantificación de horas invertidas en el proyecto a fin de definir la continuidad del mismo. 25/02/2026: El Proyecto Tarjeta Tesoro se encuentra en fase piloto, ejecutándose en un ambiente controlado de producción con la participación de dos Entidades Públicas. El piloto se mantendrá hasta el segundo trimestre de 2026, periodo en el que se evaluarán los resultados operativos, técnicos y funcionales. Paralelamente, se realizan coordinaciones con el MEF para la aprobación de los diseños de las tarjetas, los documentos normativos y la definición del calendario de implementación, necesarios para el inicio formal del servicio a nivel institucional. 21/01/2026: Marcha Blanca: En diciembre se confirmó la participación del Ministerio de Relaciones Exteriores, MEF y Tesoro Público, iniciándose las pruebas el siguiente mes. Aprobación y publicación de Directiva y Macroproceso: Se creó la Directiva “Tarjeta de crédito corporativa”, actualmente en validación; Fraude y Riesgo se encuentran pendientes de emitir opinión. Diseño y fabricación del material de difusión: La parte informativa ya fue elaborada; sin embargo, existe dependencia del MEF para el diseño de las tarjetas, sin respuesta a la fecha.terial de difusión ya se encuentra elaborada. Sin embargo, existe una dependencia del MEF para el diseño de las tarjetas, lo cual hasta el momento no se tiene respuesta. 30/11/2025: El equipo del proyecto informó que durante el mes de noviembre no hubo avances en las actividades del proyecto, El único movimiento registrado fue el envío de una carta al MEF solicitando la conformidad del diseño de las tarjetas. Se evaluará iniciar el desarrollo de la Tarjeta para los trabajadores del BN.” Esto significa que el equipo técnico está considerando avanzar con una versión interna del producto (una tarjeta dirigida a los trabajadores del Banco) mientras esperan la aprobación del MEF. Esta alternativa podría permitir avanzar parcialmente el desarrollo, pero requiere análisis formal porque podría generar cambios en alcance, tiempos o costos. 31/10/2025: Según la información enviada de Planeamiento en el mes de Octubre se precisa lo siguiente: Se presentará en el siguiente Comité de Proyectos la actualización del cronograma de trabajo 30/09/2025: Según la información enviada de Planeamiento en el mes de Septiembre se precisa lo siguiente: Se continua con las validaciones operativas en producción de manera controlada en canales BN ( ventanilla, Atm y Agente Corresponsal ) con tarjetas blancas. La nueva fecha de prueba se efectuará en la 2da semana de octubre en coordinación con el MEF. Se ha enviado una segunda carta al MEF para la aprobación de los diseños de las tarjetas. 16/09/2025:Según la información enviada de Planeamiento en el mes de Agosto se precisa lo siguiente: En el mes de agosto se confirmaron las nuevas Entidades que participarán en el último piloto de pruebas (marcha blanca) autorizado por el Ministerio de Economía y Finanzas (MEF). A estas entidades se les brindó capacitación, así como el acceso a usuarios y la entrega de tarjetas de crédito correspondientes. Asimismo, con fecha 18 de agosto, en reunión sostenida con el MEF, se aprobaron los diseños de las tarjetas, los cuales han sido remitidos al proveedor para su diagramación. Finalmente, se informa que la nueva fecha de culminación de la marcha blanca ha sido programada para fines de noviembre de 2025. 21/08/2025: De acuerdo al Acta de Comité de Proyectos del 14/08 N°07-2025 se informa que: Se solicita a la Gerencia de Productos e Inclusión Financiera realizar un informe situacional del proyecto y formalizar su solicitud de cambio para el próximo Comité Ejecutivo de Proyectos. Además, se solicita a la Gerencia de Riesgos un informe de Riesgos. 18/08/25: Según la información enviada de Planeamiento en el mes de Julio se precisa lo siguiente: Avance de julio: Se realizaron coordinaciones con las entidades que participarán en la marcha blanca (piloto de prueba) autorizada por el MEF. Hito del 4 de agosto: Reunión con el Comité de Proyectos del MEF para aprobar el diseño de las tarjetas. El MEF solicitó ajustes en los colores, Dichos cambios se gestionarán con la Gerencia de Imagen y Relaciones Institucionales. Nuevo plazo: La marcha blanca concluirá a fines de octubre de 2025. Acción necesaria: En agosto se presentará el Anexo 9 para formalizar la modificación del cronograma del proyecto. 13/08/2025: De acuerdo al Acta de Comité de Proyectos del 16/07 N°06-2025 se informa que: Se solicita a la Gerencia de Productos e Inclusión Financiera asegurar que la parte contable del producto se encuentre contemplada dentro de la ejecución del proyecto. Asimismo, se precisó que aún no se contaba con la conformidad del diseño de las tarjetas, lo que es necesario para su emisión y que implica un tiempo aproximado de dos meses de acuerdo a lo indicado por la Gerencia de Administración y Logística. 18/07/2025: Se culminará en el ambiente de producción los ciclos de prueba y las mejoras a los reportes contables / operativos del producto. El retraso de las actividades se debe a que el MEF modificó las Unidades Ejecutoras para el piloto en producción, motivo por el cual se están realizando las coordinaciones con la nueva Unidad Ejecutora. Se está a la espera de la confirmación del diseño de tarjetas y la normativa del MEF. Se estima que la marcha blanca culmine en Setiembre 2025 en paralelo con las demás actividades pendientes. 11/06/2025:Según la información enviada de Planeamiento en el mes de Mayo se precisa lo siguiente: La demora en el pase a Producción Fase IV está afectando la fase de marcha blanca. Además, la reciente solicitud de especificar los procesos contables podría obligar a un control de cambios en mayo para ajustar el plan original del proyecto. 03/06/2025: Según la información enviada de Planeamiento mediante correo respecto al proyecto en el mes de abril se tiene que: La conclusión total del servicio requiere la colaboración de las unidades orgánicas participantes. A la vez, el equipo de Desarrollo del BN trabaja en los cinco entregables finales, la certificación y el pase a producción, abordando los retrasos actuales. 21/05/2025: Según el Acta de Reunión N°04-2025 del Comité de Proyectos, se solicita a Planeamiento hacer seguimiento al proyecto y que este incluya la parte contable. 07/05/2025: Según la información remitida por Planeamiento mediante correo: Se han completado 5 de los 10 entregables. A pesar de los retrasos de Izipay, las pruebas en POS comenzarán en abril. El equipo de Desarrollo del BN trabaja para cumplir los plazos y completar los entregables restantes. 31/12/2024: Ciclos de pruebas en marcha (379 Ok / 617 Total). Se esta coordinando y resolviendo día a día con proveedor y TI. A la par ya culminaron con remitir solicitud de cambio y cronograma de actividades para que sea aprobado por el comité. 13/05/2024 A la espera del Anexo 1 para poder incorporar el proyecto a la Demanda Estratégica 25/04/2024 Mediante Memo N° 63-2024-BN2810 en que se entrega la nueva lista de proyectos con componente TI se crea el proyecto en base de datos y se asigna el Lider usuario al proyecto, anteriormente no existia .
A35: 33 | B35: PROPBMBI-EO10-24-36 | C35: Plataforma Banca Móvil y Banca por Internet | D35: El Banco de la Nación requiere urgentemente un proceso de modernización de sus plataformas de canales digitales, principalmente para implementar nuevas funcionalidades, integra más servicios para nuestros clientes, simplificar su presentación y diseño con conceptos de interfaz y experiencia de usuario; y ofrece mayor seguridad a toda la transacción de inicio a fin. Esta modernización debe considerar la utilización de una nuev plataforma tecnológica que le permita incrementar capacidades d procesamiento y recursos de cómputo de manera ágil y flexible. | E35: Banca Digital | F35: Alexis Junchaya | G35: Alexis Junchaya | H35: Ennio Palomino | I35: 29429839 | M35: 45418 | N35: Acta Nº4-2024 | O35: Servicio a los Clientes | P35: De cara al ciudadano | Q35: 2023 | R35: 2026 | S35: 3 | T35: Si | U35: Sí | V35: Banca Móvil / Banca por Internet | W35: Si | X35: Anyelina Cortez / Stephanic Urtecho | Y35: 44972 | Z35: 46508 | AA35: 0.52 | AB35: 0.36 | AC35: =Tabla3[[#This Row],[% Avance ejecutado]]-Tabla3[[#This Row],[% Avance Planificado]]/Tabla3[[#This Row],[% Avance Planificado]] -> -0.64 | AD35: 02. En Curso | AE35: 14/04/2026: En el mes de marzo se presentaron redefiniciones tecnológicas que generaron retrasos en el cronograma —Clave Dinámica Digital (15/08/2025 – 04/03/2026), Encriptación del PIN y del PAN (30/10/2025 – 10/03/2026) y Redefinición del acceso y arquitectura del Mainframe (26/01/2026 – 13/03/2026), entre el 05/03/2026 y 10/03/2026 PERUAPPs cambió personal clave por la reevaluación de lo avanzado en documentación de calidad y desarrollo, realizando una revisión total; adicionalmente, se solicitó apoyo a la Gerencia de TI para asignación de personal a tiempo parcial que valide y anticipe requerimientos técnicos del proveedor, sin obtener respuesta acorde a la magnitud del proyecto, constituyendo stoppers que impiden el comienzo integral sin reproceso proyectado para el 26/11/2025. 20/03/2026: Según el acta de reunión del comité de proyectos del mes de enero, si bien el proyecto cumplió en diciembre 2025, se han redefinido puntos pendientes de resolución: a) la clave dinámica digital será realizada por el proveedor, b) la encriptación del PIN y PAN de la tarjeta será realizada por un proveedor distinto al principal, y c) se encuentra pendiente confirmación del componente de arquitectura (WAS). Debido a ello, las pruebas funcionales no han iniciado aún. 25/02/2026: El 30/01/2026 TI emitió el informe técnico de conformidad e Innovación Digital el acta de conformidad, recogida por PERUAPPs; sin embargo, persisten tres stoppers que afectan las pruebas funcionales: definiciones pendientes de PERUAPPs sobre la Clave Dinámica Digital (TI solicitó diagrama de arquitectura), la redefinición del Microservicio de Encriptación pendiente desde octubre 2025 sin entrega por el BN, y un nuevo stopper del 26/01/2026 por la redefinición de la arquitectura de llegada al Gateway, pese a lo definido en setiembre 2025. 21/01/2026: Durante el mes de diciembre se identificaron nuevos requerimientos de seguridad, incluyendo la implementación de un dispositivo de encriptación, para lo cual TI–Seguridad elabora un TDR; este requerimiento impacta el proceso de enrolamiento de la tarjeta de débito. Asimismo, se identificó un requerimiento emergente para integrar SARAWEB al proyecto y se coordinó con Fraudes la disponibilidad de información para el repositorio institucional, condicionada a que Sentinel esté operativo para el MVP 2. Finalmente, continúan las gestiones con OSIPTEL, con demoras en las respuestas que podrían afectar el cronograma del proyecto. 30/11/2025: "En el mes de noviembre se brindado las conformidades de: - Informe de Consumo en Nube del Mes de Abril - 2025. - Informe de Consumo en Nube del Mes de Mayo - 2025. A su vez el 21/11/2025 TI brindo el informe de conformidad técnica Informe_N-66-BN-2530 del CNAPP A su vez se manifiesta que las coordinaciones y configuraciones del Antibot de Radware el cual es un componente de seguridad del BN, esta manteniendo coordinaciones emergentes entre los equipos de BN, RADWARE y PERUAPPs, lo cual ha denotado solicitudes aplazamiento del plazo limite de entrega de parte del PERUAPPs, dado que las coordinaciones del BN continuan con los equipos de RADWARE y a la fecha se estima la entrega del Informe del antibot el 11/12/2025 por parte de PERUAPPs." 31/10/2025: Según la información enviada de Planeamiento en el mes de Octubre se precisa lo siguiente: "El 6 de octubre de 2025 se otorgó la conformidad al informe correspondiente a la infraestructura del ambiente de aseguramiento de calidad (QA). Asimismo, se brindó la conformidad respecto al consumo del mes de marzo de los componentes de la infraestructura base, al despliegue del componente de seguridad Firewall y al componente de seguridad WAF de F5. Actualmente, se encuentra en proceso de implementación el componente de seguridad CNAPP. Por otro lado, se ha solicitado a la Gerencia de Planeamiento y Control de Gestión la emisión de un control de cambios con el fin de sincerar la ejecución del cronograma del proyecto." 30/09/2025: Según la información enviada de Planeamiento en el mes de Septiembre se precisa lo siguiente: Durante setiembre se registraron avances sostenidos en la implementación de la infraestructura del ambiente de aseguramiento de calidad (QA), el entorno de seguridad, así como en la revisión de la configuración de servidores y el acceso a la base de datos. Sin embargo, en el desarrollo del cronograma, el proveedor y el Banco de la Nación identificaron actividades no previstas que requirieron un plazo adicional de treinta y nueve (39) días. Estas acciones que incluyeron la habilitación de accesos, instalación de software especializado, documentación de los servicios del BDUC y WEB6000, definiciones para la implementación de la Clave Dinámica Digital en la nube y configuraciones asociadas a componentes antifraude y control de listas PEP resultaron esenciales para garantizar las condiciones técnicas y de seguridad previas al inicio de la etapa de Codificación y Pentesting del MVP1. En ese contexto, se viene gestionando un control de cambios con el fin de actualizar y sincerar el cronograma del proyecto, incorporando las actividades adicionales identificadas. 16/09/2025: Según la información enviada de Planeamiento en el mes de Agosto se precisa lo siguiente: Actualmente se esta realizando avances significativos en la implementación de la infraestructura del ambiente de QA, lo que ha permitido sentar las bases para las siguientes actividades del proyecto. La actividad debía concluir el 05/03/2025; sin embargo, su desarrollo se vio afectado por el desplazamiento de las fechas originales del cronograma, debido al retraso en la entrega del Análisis Funcional y a la necesidad de elaborar una Adenda vinculada al entregable de Infraestructura Base, motivada por la incorporación de una definición técnica no contemplada en los términos de referencia. Como consecuencia, algunas actividades tecnológicas presentan retrasos asociados al despliegue de la infraestructura del ambiente base. Esta situación fue documentada en la Adenda N.° 2, donde se sustenta la reprogramación de la fecha de entrega. Actualmente, se proyecta concluir esta actividad el 18/09/2025. 21/08/2025: De acuerdo al Acta de Comité de Proyectos del 14/08 N°07-2025 se informa que: Se solicita a la Gerencia de Banca Digital realizar un informe situacional del proyecto y formalizar su solicitud de cambio para el próximo Comité Ejecutivo de Proyectos. 18/08/25: Según la información enviada de Planeamiento en el mes de Julio se precisa lo siguiente: El proyecto tiene un retraso de aproximado de 5 meses por demoras en el análisis funcional (finalizado el 30/06) y en el diseño de cómo se ve y se usa la aplicación (finalizado el 08/07). Las adendas del contrato y cartas al proveedor modificaron plazos clave, incluyendo los servicios en la nube. El plazo contractual de 420 días es limitado y se evidenció falta de experiencia técnica del proveedor. 13/08/2025: De acuerdo al Acta de Comité de Proyectos del 16/07 N°06-2025 se informa que: La Gerencia de Banca Digital indicó que se llevará a cabo una adenda con el proveedor del proyecto. En virtud de ello, se solicita se disponga las medidas necesarias para llevar a cabo la firma de la adenda. 18/07/2025: Presenta retrasos debido al incumplimiento de (03) entregables por parte de la empresa contratada: *Funcionalidad (Casos de Uso), actualmente Banca Digital está procediendo a hacer la verificación del cumplimiento de lo solicitado según TDR para emitir el acta de conformidad. infraestructura y user testing. *Infraestructura: Se ha completado el informe técnico sobre la infraestructura base en la nube sobre la cual se desplegará el desarrollo del proyecto. TI procederá con la revisión, para según conclusión, emitir el acta de conformidad respectiva. *Diseño UX/UI – Experiencia de usuario: al 90% concluido el informe UX/UI, el cual se encuentra pendiente de ingreso por parte del proveedor para su conformidad. 11/06/2025:Según la información enviada de Planeamiento en el mes de Mayo se precisa lo siguiente: Incumplimiento de (03) entregables por parte de la empresa contratada relacionados a los temas de funcionalidad (Casos de uso), infraestructura y user testing. Cabe resaltar que se firmó la adenda de mejora el 30.05.2025; sin embargo, está pendiente el cronograma consensuado con TI. El área usuaria gestionará la solicitud de cambios por parte del área líder del proyecto 03/06/2025: Según la información enviada de Planeamiento mediante correo respecto al proyecto en el mes de abril se tiene que: Se cuenta en proceso de subsanaciòn por parte del proveedor, lo relacionado a la culminación de los casos de uso y observaciones del user testing efectuado. Asu vez, la adenda de mejora evaluada por el área legal cuenta con el informe de TI, el cual será remitido a la Gerencial General para su aprobación. Se estima presentación de solicitud de cambios previo informe posterior a rpta de GG. 02/06/2025 En daily del 29/5/2025 se indico que Segunda Adenda se encuentra en Logistica. Asimismo las Epicas 1 y 2 se encuentraban firmadas y en procesos de firmas la Epica 3. 23/05/2025: Se registra el Proyecto Nueva Plataforma de Banca Móvil y Banca por Internet. Se registró en el Backlog. 07/05/2025: Según la información remitida por Planeamiento mediante correo: Se encuentra pendiente por parte del proveedor subsanar las observaciones formuladas a los casos de uso; por lo que aún no habrá acta de conformidad y se preparará informe de penalidad. 07/05/2025: Se cambió el nombre del Proyecto "Nueva app BN y Nuevo Home Banking "Multired Virtual" "a Plataforma de Banca Móvil y Banca por Internet, según lo remitido por Planeamiento. 30/4/2025: Se tuvo reunión con el equipo técnico de TI, equipo de Banca Digital y Gerencia General se respondieron las consultas técnicas y se quedo a las la espera del pronunciamiento de Banca Digital sobre los precios unitarios. 22/4/2025: Se firmó Carta de Compromiso (Carta N° 018-2025-BN/7901) relacionado a las actividades en curso. 31/03/25: En respuesta a la Carta 009-PCDBN-PERUAPPS-2025 - "Entrega de Informe de Despliegue de la Implementación de la Infraestructura Base en AWS para los ambientes a Implementar (Desarrollo, Certificación y Producción)" se emite el infirme técnico N° 00000005 - 2025-BN/2550 el 05.03.2025 en el cual se remiten observaciones al entregable. El contratista remite la Carta 015-PCDBN-PERUAPPS-2025 - "Respuesta a Observaciones al Informe de Implementación Base de la Infraestructura AWS" y se emite el Informe Técnico 00000008 - 2025-BN/2550 el 31.04.2025 (se envió a través de correo) en el cual se solicita al contratista ampliar el sustento técnico y realizar ajustes al informe presentado. Se está a la espera de la respuesta del Contratista para que TI emita un nuevo informe el cual para que el área usuaria pueda solicitar la Adenda. Las actividades de Despliegue del ambiente DEV no se puede iniciar hasta la conformidad del despliegue de la Infraestructura Base AWS. 28/02/25: TI se encuentra participando en reuniones técnicas con el proveedor. Se tuvo reunión con el Contratista el 17/02 en el cual presentaron la "Matriz de Requerimiento – Implementación Infraestructura Base AWS v1.0" en dicho cuadro se mostró componentes que no están incluidos en los TdR y componentes que si están incluidos en los TdR, sin embargo no se tenía la claridad si se estaba cumpliendo con todo lo indicado en los TdR. El equipo de Arquitectura elaboro una matriz con todos los ítems indicados en los TdR (funcionalidades, características) a fin que el contratista defina con que herramienta y/o componente se cubría lo indicado en los TdR, esto se remitió con la Carta N°003-2025-BN/7901 de fecha 25.02. Se indico al area responsable del contraro que coordine con Logista a cerca de los diferenciales (componentes que se indicaban en la matriz presentada por el contratista y que no están indicado en los TdR. 17/02/25: TI se encuentra participando en reuniones técnicas con el proveedor y en reuniones de trabajo funcional (opcional). El 17.02 El contratista remitió la Matriz de Trazabilidad de Requerimientos correspondiente al despliegue y se agendara reuniones para la revisión. 31/02/25 El avance Sobre las actividades de Implementación de Infraestructura Cloud (AWS) 43% y Sobre las actividades del Diseño, desarrollo e implementación de la solución 12% En esta ultima actividad me indicaron que han avanzado con la elaboracion de 59 CU de un total de 286
A36: 34 | B36: PROSPOPEMSS-OE08-25-38 | C36: Solución del procesamiento de operaciones de pagaduría del Estado MEF-SIAF Y SUNAT | D36: El Banco de la Nación requiere una solución integral de software en modalidad On Premise y que además se reutilicen algunos componentes con que ya cuenta actualmente el Banco, encontrándonos en la capacidad de mejorar y ampliar la capacidad de procesamiento de lotes con órdenes de transferencias provenientes del sistema SIAF / MEF | E36: Operaciones | F36: María Luisa Guevara | G36: Marco Ortiz | H36: Rina Roca | I36: 2815186.1 | M36: 45677 | N36: Acta Nº1-2025 | O36: Por asignar | P36: Por asignar | Q36: 2024 | R36: 2026 | S36: 2 | T36: Si | U36: Sí | V36: Pagaduría | W36: Si | X36: Eduardo Cardenas / Elia Muñoz | Y36: 45446 | Z36: 46265 | AA36: 0.63 | AB36: 0.58 | AC36: =Tabla3[[#This Row],[% Avance ejecutado]]-Tabla3[[#This Row],[% Avance Planificado]]/Tabla3[[#This Row],[% Avance Planificado]] -> -0.42 | AD36: 02. En Curso | AE36: 14/04/2026: Al cierre del mes de marzo, con respecto a la etapa de Desarrollo de la Fase I, se encuentra pendiente las guías de despliegue y documentación para el pase a certificación; lo cual ha tenido repercusión en la etapa de certificación de la Fase I. 23/03/2026: Al cierre de febrero se elaboró el cronograma para la solicitud de cambios con ampliación de plazo, coordinado con Operaciones, TI y el proveedor; la integración de AD e ISIM se realizó satisfactoriamente, y se vienen sosteniendo reuniones con SUNAT para revisar los detalles técnicos de la integración. 20/03/2026: Según el acta de reunión del comité de proyectos del mes de enero, el proyecto presentó un ligero retraso al cierre de diciembre 2025. En enero 2026 se reunió con el proveedor para realizar la integración de la solución Novatronic con el sistema de Gestión de Identidades ISIM, y se espera concluir el análisis de vulnerabilidades en enero 2026. La Gerencia de TI y Operaciones se encuentra revaluando los plazos planificados de la Fase I debido a los retrasos presentados, lo cual repercute en la Fase II del proyecto. 25/02/2026: Con respecto al análisis de Vulnerabilidades en el proceso de validación con el área de Seguridad Informatica se reportó la observación relacionada a la infraestructura, por lo que el área de infraestructura tecnológica se encuentra en subsanación. Asimismo, las referidas actividades han afectado los avances de la fase II, por lo que la Gerencia líder gestionará la solicitud de cambios, reformulando el cronograma con la finalidad de continuar con el proyecto. 21/01/2026: En la actividad de pruebas en ambiente de desarrollo, el avance pasó de 30% en noviembre a 35% en diciembre, sin progreso significativo, debido a la falta de integración de Novatronic con ISIM; el 07/01/2026 se realizó reunión con el proveedor para atender dicha integración. La Subgerencia de Contabilidad respondió el 07/01/2026, identificándose que el producto debe registrarse como nuevo canal; la Gerencia de Operaciones presentó el Anexo 2, pendiente de aprobación por la Subgerencia de Construcción de Aplicaciones. El análisis de vulnerabilidades se encuentra concluido, quedando pendiente la confirmación de Seguridad Informática. 30/11/2025: Al cierre del mes de noviembre, se viene realizando las actividades con un grado de avance mayor a lo planificado respecto al análisis y diseño de archivo de conciliación, actualización de solicitudes Lotes de la Fase I, Asimismo, se ha validado las transacciones de Pagaduría, (cargo, abono, extorno, consultas) en lo correspondiente planificado para el presente mes. 31/10/2025: Según la información enviada de Planeamiento en el mes de Octubre se precisa lo siguiente: Al 31.10.25, con la participación del proveedor Novatronic, MEF y del personal informático del Banco, se continúa ejecutando pruebas integrales en el ambiente de desarrollo, con el propósito de validar las implementaciones realizadas tanto por el Banco como por el proveedor, en el ambiente de certificación se convocará al MEF a fin de realizar pruebas integrales. Asimismo, se viene probando devoluciones y extornos de transferencias enviadas al BCRP. Se actualizó cronograma y se elaboró los documentos para la solicitud de cambios. 30/09/2025: Según la información enviada de Planeamiento en el mes de Septiembre se precisa lo siguiente: Al 30.09.25, con la participación del proveedor Novatronic, MEF y del personal informático del Banco, se continúa ejecutando pruebas integrales en el ambiente de desarrollo, con el propósito de validar las implementaciones realizadas tanto por el Banco como por el proveedor, se estima para el mes de octubre se encuentre en el ambiente de certificación. Se presentaron observaciones en el ciclo de pruebas referido a los lotes procesados del MEF (archivo de transferencias hacia otras entidades financieras vía LBTR), las cuales han sido subsanadas. Asimismo, se viene probando devoluciones y extornos de transferencias enviadas al BCRP. Por consiguiente, se ha extendido el ciclo de pruebas en el ambiente desarrollo lo que afecta las actividades siguientes. Se gestionará la solicitud de cambio, sinceramiento de cronograma proveedor y TI. 16/09/2025: Según la información enviada de Planeamiento en el mes de Agosto se precisa lo siguiente: Al cierre del mes de agosto, con la participación del proveedor Novatronic, MEF y del personal informático del Banco, se vienen ejecutando pruebas integrales en el ambiente de desarrollo, con el propósito de validar las implementaciones realizadas tanto por el Banco como por el proveedor, asegurando que estas no interfieran en la operatividad de los demás servicios y garantizando su adecuada interoperabilidad. Sin embargo, se evidencia un retraso en la implementación de la fase I, debido a: 1. Demora del MEF con la revisión de los flujos del servicio de integración LBTR-SIAF-BN 2. Coordinaciones con el BCRP a fin de revisar el proceso de conciliación que realizan las entidades. 3. Respuesta de la SUNAT a fin de confirmar su participación en la fase I. 18/08/25: Según la información enviada de Planeamiento en el mes de Julio se precisa lo siguiente: A nivel de tareas presenta un retraso debido a que la Gerencia de TI, no concluye sus pruebas unitarias en la fase de desarrollo, requisito para realizar las pruebas integrales con el usuario, MEF, Novatronic. 13/08/2025: De acuerdo al Acta de Comité de Proyectos del 16/07 N°06-2025 se informa que: Se solicita agendar reunión entre la Gerencia de Operaciones, la Gerencia de Planeamiento y Control de Gestión y, la Gerencia General para revisar la fecha fin del proyecto la cual es marzo 2026. 18/07/2025: Se está avanzando las actividades del entregable Fase I – MEF y SUNAT: En relación a las pruebas de desarrollo (Desarrollo Novatronic y Banco), el BN ha desarrollado un ambiente CICS exclusivo para el nuevo sistema de Pagaduría, con la finalidad de que no interfiera con la operatividad de otros servicios (interoperabilidad) Actividades: 1. EETT archivo de Conciliación del Banco 100% 2. Novatronic y el Banco han realizado las validaciones de conexión con FTP del MEF y resultaron conformes. 100% Se espera que las pruebas en ambiente de certificación se den en Julio 2025 11/06/2025:Según la información enviada de Planeamiento en el mes de Mayo se precisa lo siguiente: Nos encontramos en la etapa de Desarrollo y Construcción la fase I del proyecto de Pagaduría: Integración LBTR-SIAF-BCRP. En relación a las pruebas de desarrollo (Desarrollo Novatronic y Banco), además se ha comprometido la participación del MEF y BCRP, lo que implica pruebas de conectividad para este mes y en el mes de junio se realizarian las pruebas integrales entre el Banco, MEF y BCRP. Novatronic se atraso en el desarrollo de sus interfases, para el mes de mayo ha acelerado el desarrollo de sus aplicaciones. 03/06/2025: Según la información enviada de Planeamiento mediante correo respecto al proyecto en el mes de abril se tiene que: Se ha finalizado la revisión de estructuras de interfaces de todos los flujos (para las fases I y II) Se han realizado coordinaciones con el BCRP a fin de revisar el proceso de conciliación que realizan las entidades, asimismo mediante correo electrónico (02.05.2025) se ha solicitado a dicha entidad asegurar su participación en las pruebas de conectividad e intercambio de información para la ejecución de las pruebas preliminares a iniciarse en la segunda quincena de mayo del presente. Con carta Nro. 005-2025 BN3100 (29.04.2025) se comunicó a la Dirección General del Tesoro Público el estado del desarrollo que viene realizando el Banco referente a la implementación del proyecto de pagaduría para la interconexión entre los sistemas transaccionales del SIAF y LBTR del BCRP; solicitando la cooperación de su equipo técnico en las pruebas de conectividad e intercambio de información para las pruebas preliminares a realizarse en la 2da quincena de mayo del 2025. 07/05/2025: Según la información remitida por Planeamiento mediante correo: A nivel tareas, actualmente se encuentra en la Etapa de Implementación del Proyecto. - Se ha culminado la revisión de flujos y esquemas de la fase I (Integración SIAF-BN-LBTR), está pendiente de que TI confirme el desarrollo de la interfaz Host. - Se ha coordinado con TI (H. Zevallos) la asignación de un recurso adicional (Nestor Acha), que apoye a E. Cárdenas con la implementación de la TXn HOST (cargo, abono, extorno, consulta) requerido por Novatronic para la integración con el SIAF; asimismo la asignación de otro recurso para el proceso de Conciliación. - Se encuentra en la actividad de habilitación de ambiente y servidores para las pruebas funcionales de la fase I, está pendiente de que Novatronic valide la conectividad (Al mes de Abril ya se concluyo la actividad). - Pendiente una reunión entre Novatronic y TI del BN a fin de revisar el flujo de la fase II (al mes de abril ya se concluyó la actividad). 08/04/2025: Mediante el Acta de Reuniòn 01-2025 el Comitè de Proyectos aprobò el proyecto. 17/02/25 Revisión del Flujo 1 - MEF LBTR: Se remitio la informacion solictada por Novatronic. Avance: 100% . Análisis y Diseño 50% (Novatronic) Proporcionar las EETT de Txn del Host BN 50% Generacion de Archivos y Casos de Pruebas MEF/SUNAT - BN (Sunat no cuenta con la infor.) 50% 31/01/25: Aprobado en comité de Ene25. En reuniones técnicas con el proveedor. 20/05/2024 Mediante correo de Jorge Lavalle se notifica laentrega de la propuesta comercial y los TDRs para su validación,se genera reunion para su revisión el 22-05. 07/05/2024 Mediante correo se hace envìo de los TDRs del proyecto. 30/04/2024 Mediante correo de Antonio Luyo se entrega el documento de las TDr s del proyecto a Martin Nicho, para luego ser remitidas a Jorge Lavalle y Marco Ortiz. 29/04/2024 Mediante correo de Jorge Lavalle se pide la validación de los TDRs del proyecto 25/04/2024 Por correo de Martin Nicho se pide la asistencia para dar respuesta al usuario sobre los requerimientos del proyecto, se establece un orden de prioridad para la atención de los mismo: Seguridad informática, Arquitectura, Construcción y Producción. Se espera la formalización de la inscripción del proyecto a la lista de proyectos estratégicos por Jorge Lavalle. 22/04/2024 Con correo remitido por Jorge Lavalle se pone en consideración la priorización de los TDRs, una vez teniendo los TDRs finales finaliza la revisión del contrato e inicia la formalización. Se hace llegar el contrato, propuesta y, esquema general y técnico de solución.
A37: 35 | B37: PROCDBN-EO05-37 | C37: Cuenta Digital BN | D37: La Cuenta Digital BN cumplirá la misma función y objeto de la Cuenta DNI, la única diferencia será el soporte tecnológico, de esta manera, se tendrá un control y monitoreo efectivo de la plataforma que soportará la Cuenta DNI. | E37: Banca Digital | F37: Luis Palacios | G37: Luis Palacios | H37: Juan Carlos Palomino | I37: 0 | M37: 45643 | N37: Acta N°9-2024 | Q37: 2024 | R37: 2025 | S37: 1 | T37: Si | U37: Sí | V37: Cuenta Digital | W37: Si | X37: Johnny Rocca | Y37: 45418 | Z37: 46018 | AA37: 1 | AB37: 1 | AC37: =Tabla3[[#This Row],[% Avance ejecutado]]-Tabla3[[#This Row],[% Avance Planificado]]/Tabla3[[#This Row],[% Avance Planificado]] -> 0 | AD37: 02. En Curso | AE37: 20/03/2026: Según el acta de reunión del comité de proyectos del mes de enero, el proyecto presentó un ligero retraso al cierre de diciembre 2025 debido a que quedó pendiente pasar a producción el tarifario para agentes corresponsales. A inicios de enero 2026 el proyecto pasó a producción y la Gerencia de Banca Digital presentó su Acta de cierre y lecciones aprendidas del proyecto. 25/02/2026: El proyecto Cuenta Digital BN culminó satisfactoriamente, habiéndose ejecutado un piloto controlado en producción y realizado el pase final el 6 de enero de 2026, considerando que el mes de diciembre se encuentra definido como periodo de freezing, durante el cual no se realizan pases a producción. 21/01/2026: El 23 de diciembre se completo la certificación de tarifario para agentes corresponsales, estando listos para pase a producción. En diciembre no hay pases a producción. El 6 de enero paso a producción el mantenimiento de tarifario, sin embargo el canal agentes se probó el 29 diciembre 2025 pasando correctamente la consulta, retiro, deposito sin el tarifario diferenciado para agentes. 30/11/2025: "El proyecto aún no puede avanzar al siguiente entregable final, porque falta concluir un conjunto de pruebas técnicas en el ambiente de Calidad de TI. Estas pruebas están relacionadas con el tarifario - agentes, que es un componente necesario para completar la funcionalidad del proyecto. Mientras estas pruebas no se terminen y validen correctamente: No se puede cerrar la fase actual, y No se puede ejecutar el “piloto controlado producción”, que es la siguiente entregable para validar el servicio con usuarios reales." 31/10/2025: Según la información enviada de Planeamiento en el mes de Octubre se precisa lo siguiente: Nos encontramos en los lineamientos estratégicos para la soliciutd de cambio del proyecto, en coordinación con la Gerencia de Operaciones, Banca Digital y la Subgerencia de Construcción de Aplicaciones. 30/09/2025: Según la información enviada de Planeamiento en el mes de Septiembre se precisa lo siguiente: El avance del proyecto se ha visto afectado por limitaciones en el soporte técnico interno y problemas de conectividad con la Cámara de Compensación, lo que ha dificultado la ejecución oportuna de pruebas críticas. Asimismo, la baja disponibilidad del personal del área de negocio ha generado retrasos en las actividades de validación y aprobación de entregables. Finalmente, la demora en la definición del tarifario de comisiones ha impedido completar la configuración de parámetros y la realización de pruebas integrales, impactando en la planificación general del proyecto y en la coordinación entre los equipos técnicos y funcionales. 16/09/2025: Según la información enviada de Planeamiento en el mes de Agosto se precisa lo siguiente: El mantenimiento del Proceso de Apertura Masiva Batch de Cuentas Digitales BN (Código 2024-M0218) culminó satisfactoriamente su etapa de certificación y se encuentra a la espera de autorización para el pase a producción. El entregable “Tabla de Control de Calidad” (Código 2024-M0465) ha concluido su implementación y ya se encuentra en producción. 21/08/2025: De acuerdo al Acta de Comité de Proyectos del 14/08 N°07-2025 se informa que: Se solicita a la Gerencia de Banca Digital realizar un informe situacional del proyecto y formalizar su solicitud de cambio para el próximo Comité Ejecutivo de Proyectos. Además, se solicita añadir el tarifario correspondiente dentro del proyecto. Asimismo, se solicita a la Gerencia de Riesgos y Gerencia de Oficialía de de Cumplimiento Normativo y Conducta de Mercado que evalúen el proyecto dentro de sus competencias. 18/08/25: Según la información enviada de Planeamiento en el mes de Julio se precisa lo siguiente: El proyecto de apertura de Cuentas Digitales BN en Línea (M0098) pasó a producción antes de lo previsto. Se avanza en la certificación de la apertura masiva (M0218), con dos tareas pendientes en el host y cierre estimado para el 13/08/2025. El proyecto “Tabla de Control de Calidad” (M0465) culminó la certificación y espera pase a producción. Se establecieron los lineamientos estratégicos para la migración, en coordinación con las Gerencias de Operaciones, Banca Digital y la Subgerencia de Construcción de Aplicaciones. 18/07/2025: En el marco del proyecto de apertura de Cuentas Digitales BN en Línea: Mantenimiento individual y masivo – Código 2024-M0098, pasó a producción. Asimismo, continúa la ejecución de pruebas de certificación correspondientes al proceso de apertura masiva batch de Cuentas Digitales BN (Código 2024-M0218).En relación con el proyecto “Tabla de Control de Calidad” (Código 2024-M0465), continua en etapa de pruebas dentro del entorno de certificación. Se definieron los lineamientos estratégicos para la migración, en coordinación con la Gerencia de Operaciones, Banca Digital y la Subgerencia de Construcción de Aplicaciones 11/06/2025:Según la información enviada de Planeamiento en el mes de Mayo se precisa lo siguiente: Realizando pruebas de proceso de apertura masiva Batch de Cuentas Digitales BN (Código 2024-M0218) en el ambiente de certificación. En relación al entregable “Tabla de Control de Calidad” (Código 2024-M0465), este también se encuentra en pruebas dentro del entorno de certificación. Se concluyó la definición de estrategia de migración, realizado por la Gerencia de Operaciones, Banca Digital y la Subgerencia de Construcción de Aplicaciones. 03/06/2025: Según la información enviada de Planeamiento mediante correo respecto al proyecto en el mes de abril se tiene que: Se logró concluir con las pruebas en ambiente de desarrollo para el proceso de apertura de Cta. Digital BN en Línea (individual y masivo - 2024-M0098). Se han realizado las reuniones de entendimiento con la Sección Control de Calidad, Sección Sistemas Bancarios y la Sección Arquitectura de Datos y Aplicaciones. Se encuentra en proceso las pruebas en ambiente de certificación con el apoyo del área usuaria Sección Apertura de Cuentas. Se concluyó las pruebas en ambiente de desarrollo para el proceso de Apertura masiva batch de Cta. Digital BN (2024-M0218), se encuentra en proceso las reuniones de entendimiento con la Sección Calidad para iniciar las pruebas en ambiente de certificación. La Sección Control de Calidad realizó observaciones al proceso Tabla de Control calidad (2024-M0465), las mismas que fueron revisada y subsanadas por la l Sección Servicios Bancarios. Se están preparando para indicar las pruebas en certificación Se establecieron los lineamientos para la estrategia de migración, en conjunto la Gerencia de Operaciones, banca Digital y la Subgerencia de Construcción de Aplicaciones. 07/05/2025: Según la información remitida por Planeamiento mediante correo: A nivel tareas, actualmente se encuentra en la Etapa de Implementación del Proyecto. Continúan las pruebas en desarrollo con la participación de los usuario (Secc. Apertura de Cuentas) y la fabrica de SW del BN, encargada de los desarrollo, para el componente 2024-M0098 - Adecuación proceso de apertura de cta. DNI en Linea (individual y masivo ), actividad que presenta atraso y perjudica el avance de otras actividades (pruebas en canales). Las pruebas con los canales de atención se encuentra en pausa, hasta que Continúan las pruebas en desarrollo con la participación de los usuario (Secc. Apertura de Cuentas) y la fabrica de SW del BN, encargada de los desarrollo, para el componente 2024-M0218-Apertura masiva batch. Se viene coordinando las actividades previas para iniciar la pruebas en certificación, como es la carga inicial de los DNI's, para el componente 2024-M0465-Tabla de Control. 03/02/2025 Este proyecto tiene los mantenimientos: 2024-M0098: Adecuación Proceso de Apertura de CTA DNI en Linea (individualy masivo) y funcionamiento en canales de atencion: Se encuentra en pruebas con usuario Ambiente de Desarrollo 2024-M0218: Apertura Masiva batch: Se encuentra en pruebas con usuario Ambiente Desarrollo 2024-M0645: Tabla de Control: El 05/02 Inician las pruebas con usuario Ambiente Desarrollo. 31/01/25: Aprobado en comité de Dic24. Se encuentra en proceso de Desarrollo.
A38: 36 | B38: PROASAHEH-EO10-25-41 | C38: Adquisición del Sistema de Almacenamiento y Eq. Brocade (High-End Hitachi) | D38: Adquisición de Solución de Sistema de Almacenamiento High End Hitachi y Director Brocade o equivalente para los tres centros de datos del Banco de la Nación, esta adquisición incluye 3 Storage High End Hitachi o equivalente (una por cada centro de cómputo) y 4 directores brocade o equivalente para la red SAN (dos por cada centro de cómputo de Lima), estos equipos brindarán soporte a los servicios productivos críticos para el BN y permitirá replicación de tipo Tri-Datacenter, es decir podremos contar con la información procesada en los Storage High End Hitachi o equivalente de los servicios productivos principales del Banco replicados a través de los tres centros de cómputo | E38: Tecnologías de Información | F38: Alejandro Sifuentes | G38: - | H38: Noe Figueroa | I38: 18108799 | M38: 45735 | N38: Acta Nº3-2025 | O38: Tecnológica | P38: De cara al ciudadano | Q38: 2023 | R38: 2025 | S38: 0 | T38: Si | U38: Sí | V38: Hitachi | W38: Si | X38: Edward Torres | Y38: 45245 | Z38: 45912 | AA38: 1 | AB38: 1 | AC38: =Tabla3[[#This Row],[% Avance ejecutado]]-Tabla3[[#This Row],[% Avance Planificado]]/Tabla3[[#This Row],[% Avance Planificado]] -> 0 | AD38: 03. Implementado | AE38: IMPLEMENTADO 30/09/2025: Según la información enviada de Planeamiento en el mes de Septiembre se precisa lo siguiente: Al cierre de setiembre, el proveedor cumplió la totalidad de las actividades programadas conforme al cronograma establecido. De acuerdo con esto, se da por culminado el proyecto. 16/09/2025: Según la información enviada de Planeamiento en el mes de Agosto se precisa lo siguiente: Al cierre del mes de agosto, el proveedor culminó con las actividades de la etapa de implementación del proyecto de acuerdo con el cronograma planificado. Asimismo, se ha iniciado la elaboración del informe de cierre del proyecto y la recopilación de las lecciones aprendidas. 21/08/2025: De acuerdo al Acta de Comité de Proyectos del 14/08 N°07-2025 se informa que: Se aprueba la solicitud de cambio en el monto de la prestación principal del proyecto. 18/08/25: Según la información enviada de Planeamiento en el mes de Julio se precisa lo siguiente: Al cierre del mes de Julio, el proveedor concluyó con la instalación de los equipos en la Sede de Chiclayo. Actualmente, se encuentran en ejecución las actividades de Puesta en funcionamiento (Configuración y Migración) de los equipos. 18/07/2025: A nivel tareas al 30.06.25, el Equipo Técnico del proyecto informó que el proveedor está cumpliendo con las actividades programadas según el cronograma establecido. Asimismo, el proveedor culminó con la entrega de los bienes en las 03 sedes y finalizo la instalación de los equipos en las sedes de San Isidro y San Borja. En Chiclayo, la instalación se realiza de forma anticipada al plan previsto. 16/06/2025: Se registró en el Backlog. Proyecto aprobado en Comité Ejecutivo de Proyectos, mediante acta N°3 del 19/03/2025. 11/06/2025:Según la información enviada de Planeamiento en el mes de Mayo se precisa lo siguiente: Se encuentra en la fase de implementación, el equipo técnico del proyecto informó que el proveedor está cumpliendo con las actividades programadas según el cronograma establecido. Cabe indicar que el proveedor culminó anticipadamente con la entrega de los bienes en la sede de San isidro y Chiclayo. 03/06/2025: Según la información enviada de Planeamiento mediante correo respecto al proyecto en el mes de abril se tiene que: Se encuentra en la fase de implementación, el equipo técnico del proyecto informó que, el proveedor está cumpliendo según el cronograma con la entrega de bienes en las 3 sedes (San Isidro, San Borja, Chiclayo). 08/04/25: Mediante Acta de Reunión 03 - 2025 el Comité de Proyectos aprobó el proyecto y se solicita que remitan su análisis de costo beneficio y su plan de trabajo detallado para su seguimiento y respectiva planificación.
A39: 37 | B39: PROMSFBN-EO12-25-39 | C39: Mejoramiento de los servicios financieros del BN a nivel Nacional (BID) | D39: El proyecto considera tres componentes. El Componente 1 se centra en el mejoramiento de la capacidad institucional mediante la implementación de estrategias y metodologías que forman parte de la capacidad organizacional. Por ejemplo, el diseño e implementación de una estrategia de transformación digital, la creación de un sistema de gestión del cambio, y el desarrollo de metodologías para productos financieros digitales son acciones que, aunque implican la utilización de tecnología, están orientadas a la estructuración y optimización de procesos internos y al fortalecimiento del capital humano, aspectos que son inherentemente intangibles. | E39: Unidad Implementadora BN/BID | F39: Eduardo Ibarra | G39: - | H39: Maria Isabel Elguera | I39: 246066263 | M39: 45677 | N39: Acta Nº1-2025 | Q39: 2025 | R39: 2030 | S39: 0 | T39: Si | U39: No | V39: BID | W39: No | X39: Por definir | Y39: 45839 | Z39: 47484 | AA39: 0.09 | AB39: 0.06 | AC39: =Tabla3[[#This Row],[% Avance ejecutado]]-Tabla3[[#This Row],[% Avance Planificado]]/Tabla3[[#This Row],[% Avance Planificado]] -> -0.94 | AD39: 02. En Curso | AE39: 14/04/2026: En el mes de marzo, COMPONENTE 1: se postergó la implementación de “Uso de canales de comunicación digital” y “Gestión del cambio” para 2027 en coordinación con el BID, impactando el avance por repriorización y demora en contratación; no obstante, se superó lo planificado en gestión documental digital (cero papel) y se culminaron TDR clave. COMPONENTE 2: se presentaron demoras por la alta complejidad en la selección de especialistas del Core Bancario, afectando TDR y arquitectura; además, se cambió la modalidad de contratación a Licitación Pública Internacional (LPI). COMPONENTE 3: ampliaciones de plazo y observaciones de proveedores retrasaron contrataciones (AntiBots, Seguridad SDLC y Nube); sin embargo, se lograron avances superiores a lo planificado en TDR de ciberseguridad (SOC y gestión de riesgos), cumpliendo el 10% programado. 23/03/2026: Para el cierre de febrero, durante la ejecución se identificaron problemas clave: desalineación entre los procedimientos del BID y los del Banco de la Nación, junto con limitado conocimiento normativo; restricciones de acceso de consultores a sistemas y herramientas, afectando su desempeño; y demoras en la contratación de especialistas para el Core Bancario debido a su alta especialización y escasa disponibilidad en el mercado. 20/01/2026: Según el acta de reunión del comité de proyectos del mes de enero, la Unidad Implementadora BN/BID viene elaborando el cronograma detallado del proyecto, el cual será presentado en enero 2026 al Directorio para un mejor seguimiento. La gerencia responsable debe presentar dicho cronograma detallado al Directorio y un cronograma de mitad de año que permita realizar el seguimiento y monitoreo de las actividades realizadas. 25/02/2026: La gerencia líder remitió a planeamiento el cronograma del proyecto correspondiente al componente al 1,2 y 3. 21/01/2026: 1.Plan de Corto Plazo: Elaboración y aprobación del Plan de Corto Plazo (100%). 2.Plan de Ejecución del Proyecto BN/BID: Elaboración y aprobación del Plan del Proyecto (100%). 3.Manual de Procedimiento – Gestión de Compras UIP (Flujo 3 – Gestión de Pago): Elaboración de la MAPRO, piloto y aprobación del Flujo 3 (100%). 4.Contratación de especialistas y analistas (grupo 2): TDR, formalización de requerimiento, proceso de contratación, no objeción del BID y suscripción de contrato (100%). 5.Designación de representantes de áreas usuarias: Solicitud a áreas usuarias (100%) y designación de representantes (80%). 6.Asignación de chequera para pagos a consultores (UIP): Solicitud a TI (100%) y entrega de chequera a la UIP (50%). 7.Contratación de Analistas Técnicos del Proyecto BN/BID: Elaboración de Términos de Referencia (100%). 30/09/2025: Según la información enviada de Planeamiento en el mes de Septiembre se precisa lo siguiente: Se realizó el “Taller de Arranque” y el “Evento Protocolar de Inicio del Proyecto". Se cumplieron con todas las condiciones previas para solicitar el 1er. Desembolso del BID. Se contrataron a los 4 Coordinadores de la Unidad Implementadora. Se aprobó en Sesión de Directorio N° 2578 de fecha 19.09.2025 el “Manual Operativo del Proyecto”. 16/09/2025:Según la información enviada de Planeamiento en el mes de Agosto se precisa lo siguiente: Durante el mes de agosto 2025 se realizaron las actividades siguientes: Se contrato al Coordinador General. Se revisaron con el BID el “Manual Operativo del Proyecto” y el “Informe de Sistema de información financiera y estructura de control interno”. Se publicó la convocatoria para la contratación de los 4 Coordinadores de la Unidad Implementadora Se inicio las coordinaciones con el BID para el desarrollo del “Taller de Arranque” y el “Evento Protocolar de Inicio del Proyecto”. 21/08/2025: De acuerdo al Acta de Comité de Proyectos del 14/08 N°07-2025 se informa que: Se solicita que, a través de la Gerencia de Planeamiento y Control de Gestión, el Coordinador General del proyecto realice una presentación del proyecto en el próximo Comité de Gerentes. También se solicita proponer la estrategia de comunicación y gestión de cambios respecto al proyecto. Además, se reitera que todos los nuevos proyectos que se incorporan al Portafolio de Proyectos deben presentar los siguientes documentos: Ficha de Iniciativa, Caso de Negocio y Acta de Constitución visada, firada y alinada entre sí. 18/08/25: Según la información enviada de Planeamiento en el mes de Julio se precisa lo siguiente: Inicio del proceso de contratación de los 4 Coordinadores de la Unidad Implementadora. 18/07/2025: Durante el mes de junio 2025 se realizaron las actividades siguientes: En relación al BN: Respuesta de FONAFE sobre contratación a plazo determinado del Coordinador General. Se definió que la contratación de los 5 coordinadores será mediante contratación directa con cumplimiento de perfil bajo la modalidad de plazo fijo. Se elaboró la propuesta de Presupuesto correspondiente a los años 2025 y 2026. Ministerio de Economía y Finanzas – MEF: Firma y Remisión del Convenio de Traslado de Recursos con el MEF. Se realizó el Primer pago al MEF por Comisión del Préstamo BID. Firma y remisión al MEF de la Carta Mandato Irrevocable de Débito Automático en mérito a la operación de endeudamiento con el BID. Banco Interamericano de Desarrollo - BID : Envío al BID del Proyecto de Manual Operativo del Proyecto para su revisión y comentarios. Se envió solicitud de apoyo al BID - Cooperación Técnica PE-T1597 (Apoyando la Transformación Digital y Sostenible del BN) 11/06/2025:Según la información enviada de Planeamiento en el mes de Mayo se precisa lo siguiente: El 05 de mayo del presente en la Sesión de Directorio N° 2558 se aprobó la creación de la Unidad Orgánica Temporal denominada Unidad Implementadora Proyecto BN/BID, encargada de la ejecución física y financiera del Proyecto “Mejoramiento de los servicios financieros del Banco de la Nación a nivel nacional”. Se ha sociabilizado a las Gerencias de Finanzas y Tesorería y Legal el proyecto de Manual Operativo, para sus observaciones y/o consultas. Se tiene la conformidad del proyecto de Convenio de Traspaso de Recursos por parte del MEF y del BN. Se estima que la Resolución Suprema del MEF se publique en la 1ra. Semana de junio. 03/06/2025: Según la información enviada de Planeamiento mediante correo respecto al proyecto en el mes de abril se tiene que: Se reviso con Recursos Humanos y el BID la propuesta de los 5 perfiles de la Unidad Implementadora. Se realizó el proyecto de Manual Operativo. 07/05/2025: Mediante la información remitida por Planeamiento mediante correo: El Proyecto aún no inicia. 08/04/25: Mediante Acta de Reunión 01 - 2025 el Comité de Proyectos aprobó el proyecto.
A40: 38 | B40: PROBEFC-EO06-25-40 | C40: Banca Empresarial - Fase IV | D40: Banca Empresarial es una plataforma transaccional diseñada para optimizar la gestión financiera de nuestros clientes titulares de Cuentas Corrientes del sector público y privado. A través de una interfaz segura y eficiente, la solución permite realizar operaciones bancarias sin necesidad de acudir a nuestras agencias, alineándose con la estrategia organizacional de digitalización y modernización de servicios financieros. | E40: Operaciones | F40: María Luisa Guevara | G40: Marco Ortiz | H40: Rina Roca | I40: 0 | M40: 45735 | N40: Acta Nº3-2025 | O40: Procesos Digitales | P40: De cara al ciudadano | Q40: 2025 | R40: 2025 | S40: 0 | T40: Si | U40: Sí | V40: Banca Empresarial | W40: Si | X40: Eduardo Cardenas | Y40: 45689 | Z40: 45992 | AA40: 0.58 | AB40: 0.45 | AC40: =Tabla3[[#This Row],[% Avance ejecutado]]-Tabla3[[#This Row],[% Avance Planificado]]/Tabla3[[#This Row],[% Avance Planificado]] -> -0.55 | AD40: 04. Cerrado | AE40: CERRADO 04/11/2025: Según el acta de reunión N°08-2025 la Gerencia de Operaciones solicitó el cierre del proyecto debido a que previo a este proyecto se ha definido la necesidad de reforzar el sistema de Banca Empresarial del Banco de la Nación. 30/10/2025: Según la información enviada de Planeamiento en el mes de Octubre se precisa lo siguiente: "Al cierre del mes de octubre, Debido a los fraudes de ingenieria social presentados en la plataforma Banca Empresarial (fraudes externos), la Gerencia de Operaciones ha visto necesario, priorizar el fortalecimiento del proceso de afiliación de los firmantes y de su operatividad en los servicios dispuestos: Transferencias internas, interbancarias, abonos masivos y devolución al Tesoro. Por lo que,el alcance del presente proyecto se acotará a la Etapa 01, en consecuencia la etapa 02 se requerirá su implementación bajo la demanda táctica. Acción que origina se proceda con la actividad de cierre del proyecto. Se elaboró los documentos para la presentación del cierre del proyecto ante el comité de proyectos." 30/09/2025: Según la información enviada de Planeamiento en el mes de Septiembre se precisa lo siguiente: Al cierre del mes de setiembre, debido a las incidencias presentadas en la plataforma de Banca Empresarial, la Gerencia de Operaciones en coordinación con TI y Riesgos ha priorizado el fortalecimiento de afiliación de firmantes y operatividad de los servicios dispuestos: Transferencias internas, interbancarias, abonos masivos y devolución tesoro. Por lo que,el alcance del presente proyecto se acotará hasta la la Etapa 01. En consecuencia, la etapa 02 del proyecto se implementaría bajo la demanda táctica. 16/09/2025: Según la información enviada de Planeamiento en el mes de Agosto se precisa lo siguiente: Al cierre del mes de agosto, viene ejecutándose según lo planificado. Asimismo se certificó el entregable correspondiente a la primera etapa del servicio de Pago de Haberes en otras entidades financieras, encontrándose a la fecha en Producción. 13/08/2025: De acuerdo al Acta de Comité de Proyectos del 16/07 N°06-2025 se informa que: Se solicita a la Gerencia TI responder a la Gerencia de Operaciones con referencia a la prioriz ación de implementación del proyecto. 18/08/25: Según la información enviada de Planeamiento en el mes de Julio se precisa lo siguiente: Al cierre del mes de julio, se encuentra en un porcentaje mayor a lo planificado, resaltando la culminación del desarrollo de la construcción Host y modificaciones de los programas para el servicio de Pago de haberes en otras instituciones financieras. Se viene realizando la revisión de documentos en el entorno de Calidad y el respectivo Diseño de Pruebas. 18/07/2025: A nivel tareas, se concluyó con el análisis técnico del servicio pago de Haberes en Otras entidades Financieras. Mediante documento N° 0091-2025 BN - 3100, la Gerencia de Operaciones solicitó al área de Gestión de Demanda y Proyectos de la Gerencia de Tecnología de información, la priorización de implementación de la fase IV de la plataforma Banca Empresarial. Se culminó el desarrollo de la construcción Host y modificaciones de los programas CICS-Told respectivos, para el servicio de Pago de haberes en otras EEFF. 03/06/2025: Según la información enviada de Planeamiento mediante correo respecto al proyecto en el mes de abril se tiene que: A pesar de los correos enviados por el analista asigando y el subgerente de planeamiento, aún no se han presentado el cronograma ni la evaluación costo-beneficio. La justificación es que están coordinando con el área de TI, la cual tiene sus propios plazos para atender y desarrollar esas actividades. 21/05/2025: Según el Acta de Reunión N°04-2025 del Comité de Proyectos, se llevará una reunión entre la Gerencia General, Gerencia de Operaciones y la Gerencia de TI para determinar los cambios que tendrá dicho proyecto. 08/04/25: Mediante Acta de Reunión 03 - 2025 el Comité de Proyectos aprobó el proyecto y se solicita que remitan su análisis de costo beneficio y su plan de trabajo detallado para su seguimiento y respectiva planificación.
A41: 39 | B41: Iniciativa | C41: Factoring BN para MYPEs proveedoras del Estado | D41: El proyecto contempla la compra de bienes, instalación y puesta de funcionamiento de una solución de sistema de almacenamiento high end y director brocade implementada en los tres centros de datos del Banco de la Nación, esta nueva solución cuenta con mejores prestaciones tecnológicas de capacidad y perfomance, así como una mejor arquitectura de disponibilidad. | E41: Productos e Inclusión Financiera | F41: Cecilia Arias | G41: Maria Almengor | H41: Juan Carlos Palomino | I41: 558200 | J41: =Tabla3[[#This Row],[Presupuesto asignado]]/2 -> 279100 | K41: =Tabla3[[#This Row],[Valor Ganado (EV)]] -> 279100 | L41: =Tabla3[[#This Row],[Valor Ganado (EV)]]/Tabla3[[#This Row],[Costo Actual (AC)]] -> 1 | M41: 45818 | N41: Acta Nº5-2025 | Q41: 2025 | R41: 2026 | S41: 0 | T41: No | U41: Sí | V41: Factoring | W41: No | X41: No definido | AA41: 0 | AB41: 0 | AC41: =Tabla3[[#This Row],[% Avance ejecutado]]-Tabla3[[#This Row],[% Avance Planificado]]/Tabla3[[#This Row],[% Avance Planificado]] -> #DIV/0! | AD41: 01. No Iniciado | AE41: 21/08/2025: De acuerdo al Acta de Comité de Proyectos del 14/08 N°07-2025 se informa que: Hay documentos por regularizar como el Informe de Finanzas - Viabilidad financiera y la elevación al Directorio para aprobación del producto, se ha determinado que el proyecto sea considerado como iniciativa por aprobar el Comité ejecutivo de Proyectos hasta que cumpla con los documentos antes mencionados. Ante ello, cuando la iniciativa se consolide y tenga la conformidad de todas las áreas participantes, es la Gerencia de Productos e Inclusión Financiera quien debe remitir la Ficha de Iniciativa a la Gerencia de Planeamiento y Control de Gestión, para su posterior sustentación en el Comité Ejecutivo de Proyectos. Además, se reitera que todos los nuevos proyectos que se incorporan al Portafolio de Proyectos deben presentar los siguientes documentos: Ficha de Iniciativa, Caso de Negocio y Acta de Constitución visada, firada y alinada entre sí. 18/08/25: Según la información enviada de Planeamiento en el mes de Julio se precisa lo siguiente: Entregó su Acta de Constitución. Sin embargo, la gerencia líder se encuentra coordinando con áreas como riesgos, finanzas y legal. 13/08/2025: De acuerdo al Acta de Comité de Proyectos del 16/07 N°06-2025 se informa que: Se solicita a la Gerencia de Productos e Inclusión Financiera remitir a la Gerencia de Planeamiento y Control de Gestión el cronograma detallado y el Acta de Constitución del proyecto. 16/06/2025: El proyecto ha sido aprobado en el Comité del 10/06/2025.
A42: 40 | B42: PROEDDO-EO07-25-42 | C42: Aplicativo de Evaluación de Desempeño por Objetivos - EDDO | D42: El proyecto busca la implementación de un aplicativo que permita el registro, seguimiento y medición de objetivos de desempeño y metas del personal del Banco de la Nación, alineado al Modelo de Gestión Humana del corporativo FONAFE; el contar con esta herramienta brindará una solución dinámica para la gestión de objetivos de los trabajadores del banco, así mismo, permitirá optimizar los tiempos de gestión del proceso, el cual actualmente se ejecuta de manera manual. | E42: Recursos Humanos y Cultura | F42: Jenny Talavera | G42: - | H42: Juan Carlos Palomino | I42: 0 | J42: =Tabla3[[#This Row],[Presupuesto asignado]]/2 -> 0 | K42: =Tabla3[[#This Row],[Valor Ganado (EV)]] -> 0 | L42: =Tabla3[[#This Row],[Valor Ganado (EV)]]/Tabla3[[#This Row],[Costo Actual (AC)]] -> #DIV/0! | M42: 45883 | N42: Acta Nº7-2025 | Q42: 2025 | R42: 2026 | S42: 0 | T42: Si | U42: No | V42: EDDO | W42: No | X42: Darwin Valenzuela | Y42: 45717 | Z42: 46204 | AA42: 0.6 | AB42: 0.26 | AC42: =Tabla3[[#This Row],[% Avance ejecutado]]-Tabla3[[#This Row],[% Avance Planificado]]/Tabla3[[#This Row],[% Avance Planificado]] -> -0.74 | AD42: 04. Cerrado | AE42: 23/03/2026: De acuerdo al Comité de Proyectos según Acta N° 03-2026 de fecha 03 de marzo de 2026, el proyecto se retira del Portafolio de proyectos debido a que no se encuentra dentro de la lista de primera prioridad de la Gerencia de Recursos Humanos. Sin embargo, las actividades correspondientes a este aplicativo seguirán trabajándose con la Gerencia de Tecnologías de Información como demanda táctica. 20/03/2026: Según el acta de reunión del comité de proyectos del mes de enero, la Gerencia de Recursos Humanos viene trabajando en la definición de los objetivos de cada una de las gerencias usuarias del proyecto. Se encuentra pendiente contar con recursos de la Gerencia de TI para dar inicio a las actividades planificadas. La gerencia responsable debe presentar el cronograma detallado actualizado y validado del proyecto. 25/02/2026: El proyecto EDDO continúa en fase de desarrollo. Se realizó una reunión de coordinación con TI y el área usuaria, acordándose ajustes de cronograma y alcance, el fortalecimiento del proceso de pruebas y el establecimiento de reuniones diarias de seguimiento. Finalmente, se adjuntan evidencias de las actividades ejecutadas como sustento del avance del proyecto. 21/01/2026: El proyecto EDDO continúa en fase de desarrollo conforme a lo planificado. La Gerencia de TI avanzó con el segundo tramo de entregables, realizando reuniones de coordinación en diciembre de 2025 para alinear criterios funcionales y técnicos y definir ajustes a la solución. Como resultado, se acordó incorporar progresivamente la descripción de funcionalidades durante las pruebas, validar vinculaciones entre periodos y etapas, revisar la depuración de oficinas inactivas con Planeamiento, y definir opciones de búsqueda y validaciones específicas del sistema. El área usuaria mantiene las pruebas incrementales y se cuenta con evidencias del trabajo realizado. 30/09/2025: Según la información enviada de Planeamiento en el mes de Septiembre se precisa lo siguiente: El proyecto “Aplicativo de Evaluación de Desempeño por Objetivos (EDDO)” . Desde su aprobación el 21 de agosto de 2025, se han cumplido los pasos formales requeridos, incluyendo la remisión de los documentos técnicos (FI, CN, AC) y el envío del Anexo 01 a la Gerencia de TI. A la fecha (13 de octubre de 2025), el proyecto se encuentra en proceso de confirmación del cronograma de atención con la Oficina de Proyectos y Procesos de TI, lo que evidencia un avance sostenido hacia la planificación del desarrollo del aplicativo. 16/09/2025: Según la información enviada de Planeamiento en el mes de Agosto se precisa lo siguiente: El 14.08.2025 se aprobó en el Comité ejecutivo de proyectos. Luego de ello, la gerencia de recursos humanos remitió a la gerencia de planeamiento y control de gestión los documentos siguientes: Ficha de iniciativa, caso de negocio y Acta de constitución. La gerencia de planeamiento y control de gestión comunicó a la gerencia de TI que el proyecto fue aprobado. 21/08/2025: De acuerdo al Acta de Comité de Proyectos del 14/08 N°07-2025 se informa que: Toda iniciativa aprobada pasa a calificarse como Anteproyecto. Teniendo en cuenta lo mencionado y recibida la documentación correspondiente al proyecto se aprueba el anteproyecto pasando a calificarse ahora como proyecto. Además, se reitera que todos los nuevos proyectos que se incorporan al Portafolio de Proyectos deben presentar los siguientes documentos: Ficha de Iniciativa, Caso de Negocio y Acta de Constitución visada, firada y alinada entre sí. 13/08/2025: De acuerdo al Acta de Comité de Proyectos del 16/07 N°06-2025 se informa que: Se da por aprobada la iniciativa. La Gerencia de Recursos Humanos y Cultura debe remitir su Caso de Negocio para ser sustentado en el próximo Comité Ejecutivo de Proyectos.
A43: 41 | B43: Iniciativa | C43: Cero Papel | J43: =Tabla3[[#This Row],[Presupuesto asignado]]/2 -> 0 | K43: =Tabla3[[#This Row],[Valor Ganado (EV)]] -> 0 | L43: =Tabla3[[#This Row],[Valor Ganado (EV)]]/Tabla3[[#This Row],[Costo Actual (AC)]] -> #DIV/0! | V43: Cero papel | AA43: 0 | AB43: 0 | AC43: =Tabla3[[#This Row],[% Avance ejecutado]]-Tabla3[[#This Row],[% Avance Planificado]]/Tabla3[[#This Row],[% Avance Planificado]] -> #DIV/0! | AD43: 01. No Iniciado | AE43: 21/08/2025: De acuerdo al Acta de Comité de Proyectos del 14/08 N°07-2025 se informa que: La Gerencia de Planeamiento y Control de Gestión sustente en el próximo Comité Ejecutivo de Proyectos para su aprobación respectiva. Además, se reitera que todos los nuevos proyectos que se incorporan al Portafolio de Proyectos deben presentar los siguientes documentos: Ficha de Iniciativa, Caso de Negocio y Acta de Constitución visada, firada y alinada entre sí.

Sheet Demanda Estrategica CT
A1: TOTAL: | C1: =COUNT(DemandaEstrateg_[ID]) -> 111 | F1: =TODAY() -> 46161
A2: SEGUIMIENTO DE LA DEMANDA ESTRATÉGICA
AK3: OK | AL3: OK | AM3: OK | AN3: PENDIENTE | AO3: PENDIENTE
A4: ID | B4: ID Trámite | C4: ID Dependencia | D4: ID Proyecto / Mantenimiento asociado | E4: Tipo de Requerimiento | F4: Nombre del Proyecto | G4: Alcance del Proyecto | H4: Gerencia Líder | I4: Líder del Proyecto | J4: Usuario Funcional | K4: Gestor de Planeamiento | L4: Fecha de Solicitud a TI | M4: Memorando STD | N4: Canal de Atención | O4: Producto | P4: Servicio | Q4: Categoría | R4: Entidad reguladora / Organo de Control | S4: N° Norma / N° Informe | T4: N° recomendación | U4: Año Inicio Planificado | V4: Año Fin Planificado | W4: Fecha de Aprobación en Comité | X4: Presupuesto asignado | Y4: Cartera | Z4: Gestor TI | AA4: Aplicativo | AB4: Área Responsable TI | AC4: Entidad / Proveedor Asignado | AD4: Líder Técnico | AE4: Analista asignado | AF4: Motivo según estado | AG4: Fecha registro trámite | AH4: Fecha Inicio- Plan | AI4: Fecha Fin- Plan | AJ4: Fecha Fin Ral (CQ) | AK4: % Avance Planificado | AL4: % Avance ejecutado | AM4: Desv. % | AN4: Días faltantes | AO4: ALERTA | AP4: Fecha Fin TI Propuesta | AQ4: Fecha Fin TI (Trimestre) | AR4: Últ. Estado CQ 14.05 | AS4: Estado TI | AT4: Estado Proyecto TI | AU4: Seguimiento OPP | AV4: Código de Planeamiento
